Workbook

Sheet clean pnl
A1: Line Item | B1: Fiscal Year | C1: Value
A2: revenue | B2: 2016
A3: wholesale | B3: 2016 | C3: 11663
A4: retail | B4: 2016 | C4: 5841
A5: other businesses | B5: 2016 | C5: 979
A6: total net revenue | B6: 2016 | C6: 18483
A7: revenue growth y/y | B7: 2016
A8: cost of goods sold | B8: 2016 | C8: -9500
A9: gross profit | B9: 2016 | C9: 8983
A10: gross margin % | B10: 2016 | C10: 0.486
A11: royalty and commission income | B11: 2016 | C11: 108
A12: other operating income | B12: 2016 | C12: 60
A13: other operating expenses | B13: 2016
A14: marketing and point-of-sale | B14: 2016 | C14: -2532
A15: distribution and selling expense | B15: 2016 | C15: -4029
A16: general & administration | B16: 2016 | C16: -998
A17: sundry expenses | B17: 2016 | C17: -185
A18: total other operating exp. | B18: 2016 | C18: -7744
A19: goodwill / intangible impairment | B19: 2016
A20: operating profit (ebit) | B20: 2016 | C20: 1407
A21: operating margin % | B21: 2016 | C21: 0.076
A22: financial income | B22: 2016 | C22: 20
A23: financial expenses | B23: 2016 | C23: -74
A24: income before taxes | B24: 2016 | C24: 1353
A25: income tax expense | B25: 2016 | C25: -392
A26: effective tax rate % | B26: 2016 | C26: 0.29
A27: net income from continuing ops. | B27: 2016 | C27: 961
A28: net income from disc. operations | B28: 2016
A29: net income (total) | B29: 2016 | C29: 961
A30: less: minority interest | B30: 2016 | C30: -12
A31: net income attrib. to shareholders | B31: 2016 | C31: 949
A32: basic eps | B32: 2016 | C32: 4.72
A33: diluted eps | B33: 2016 | C33: 4.7
A34: wtd. avg shares - basic (mn) | B34: 2016 | C34: 201
A35: wtd. avg shares - diluted (mn) | B35: 2016 | C35: 201.8
A36: dividend per share (dps) | B36: 2016 | C36: 2
A37: revenue | B37: 2017
A38: wholesale | B38: 2017 | C38: 12943
A39: retail | B39: 2017 | C39: 7172
A40: other businesses | B40: 2017 | C40: 1103
A41: total net revenue | B41: 2017 | C41: 21218
A42: revenue growth y/y | B42: 2017 | C42: 0.148
A43: cost of goods sold | B43: 2017 | C43: -10524
A44: gross profit | B44: 2017 | C44: 10694
A45: gross margin % | B45: 2017 | C45: 0.504
A46: royalty and commission income | B46: 2017 | C46: 115
A47: other operating income | B47: 2017 | C47: 66
A48: other operating expenses | B48: 2017
A49: marketing and point-of-sale | B49: 2017 | C49: -2843
A50: distribution and selling expense | B50: 2017 | C50: -4710
A51: general & administration | B51: 2017 | C51: -1125
A52: sundry expenses | B52: 2017 | C52: -212
A53: total other operating exp. | B53: 2017 | C53: -8890
A54: goodwill / intangible impairment | B54: 2017
A55: operating profit (ebit) | B55: 2017 | C55: 1985
A56: operating margin % | B56: 2017 | C56: 0.094
A57: financial income | B57: 2017 | C57: 24
A58: financial expenses | B58: 2017 | C58: -82
A59: income before taxes | B59: 2017 | C59: 1927
A60: income tax expense | B60: 2017 | C60: -540
A61: effective tax rate % | B61: 2017 | C61: 0.28
A62: net income from continuing ops. | B62: 2017 | C62: 1387
A63: net income from disc. operations | B63: 2017
A64: net income (total) | B64: 2017 | C64: 1387
A65: less: minority interest | B65: 2017 | C65: -14
A66: net income attrib. to shareholders | B66: 2017 | C66: 1373
A67: basic eps | B67: 2017 | C67: 6.78
A68: diluted eps | B68: 2017 | C68: 6.75
A69: wtd. avg shares - basic (mn) | B69: 2017 | C69: 202.5
A70: wtd. avg shares - diluted (mn) | B70: 2017 | C70: 203.3
A71: dividend per share (dps) | B71: 2017 | C71: 2.6
A72: revenue | B72: 2018
A73: wholesale | B73: 2018 | C73: 12733
A74: retail | B74: 2018 | C74: 8196
A75: other businesses | B75: 2018 | C75: 986
A76: total net revenue | B76: 2018 | C76: 21915
A77: revenue growth y/y | B77: 2018 | C77: 0.033
A78: cost of goods sold | B78: 2018 | C78: -10607
A79: gross profit | B79: 2018 | C79: 11308
A80: gross margin % | B80: 2018 | C80: 0.516
A81: royalty and commission income | B81: 2018 | C81: 121
A82: other operating income | B82: 2018 | C82: 71
A83: other operating expenses | B83: 2018
A84: marketing and point-of-sale | B84: 2018 | C84: -2871
A85: distribution and selling expense | B85: 2018 | C85: -4909
A86: general & administration | B86: 2018 | C86: -1140
A87: sundry expenses | B87: 2018 | C87: -219
A88: total other operating exp. | B88: 2018 | C88: -9139
A89: goodwill / intangible impairment | B89: 2018
A90: operating profit (ebit) | B90: 2018 | C90: 2361
A91: operating margin % | B91: 2018 | C91: 0.108
A92: financial income | B92: 2018 | C92: 28
A93: financial expenses | B93: 2018 | C93: -91
A94: income before taxes | B94: 2018 | C94: 2298
A95: income tax expense | B95: 2018 | C95: -597
A96: effective tax rate % | B96: 2018 | C96: 0.26
A97: net income from continuing ops. | B97: 2018 | C97: 1701
A98: net income from disc. operations | B98: 2018
A99: net income (total) | B99: 2018 | C99: 1701
A100: less: minority interest | B100: 2018 | C100: -11
...

Sheet lookup tables
A1: Line Item Description | B1: Statement Group | C1: Sign Convention
A2: Wholesale | B2: Revenue | C2: Positive
A3: Retail | B3: Revenue | C3: Positive
A4: Other Businesses | B4: Revenue | C4: Positive
A5: Total Net Revenue | B5: Revenue | C5: Positive
A6: Cost of Goods Sold | B6: Cost | C6: Negative
A7: Gross Profit | B7: Subtotal | C7: Positive
A8: Royalty and Commission Income | B8: Other income | C8: Positive
A9: Other Operating Income | B9: Other income | C9: Positive
A10: Marketing and Point-of-Sale | B10: Operating expense | C10: Negative
A11: Distribution and Selling Expense | B11: Operating expense | C11: Negative
A12: General & Administration | B12: Operating expense | C12: Negative
... A28: Dividend Per Share (DPS) | B28: Per share | C28: Positive

Sheet MASTER P&L
A1: Line Item | B1: FY2016 | C1: FY2017 | D1: FY2018 | E1: FY2019 | F1: FY2020 | G1: FY2021 | H1: FY2022 | I1: FY2023
A2: revenue
A3: wholesale | B3: {=IF($A3="","",_xlfn.XLOOKUP(1,(Table1[Line Item]=$A3)*(Table1[Fiscal Year]=VALUE(RIGHT(B$1,4))),Table1[Value],"Not found"))} -> 11663 | C3: {=IF($A3="","",_xlfn.XLOOKUP(1,(Table1[Line Item]=$A3)*(Table1[Fiscal Year]=VALUE(RIGHT(C$1,4))),Table1[Value],"Not found"))} -> 12943 | D3: {=IF($A3="","",_xlfn.XLOOKUP(1,(Table1[Line Item]=$A3)*(Table1[Fiscal Year]=VALUE(RIGHT(D$1,4))),Table1[Value],"Not found"))} -> 12733 | E3: {=IF($A3="","",_xlfn.XLOOKUP(1,(Table1[Line Item]=$A3)*(Table1[Fiscal Year]=VALUE(RIGHT(E$1,4))),Table1[Value],"Not found"))} -> 13191 | F3: {=IF($A3="","",_xlfn.XLOOKUP(1,(Table1[Line Item]=$A3)*(Table1[Fiscal Year]=VALUE(RIGHT(F$1,4))),Table1[Value],"Not found"))} -> 10160 | G3: {=IF($A3="","",_xlfn.XLOOKUP(1,(Table1[Line Item]=$A3)*(Table1[Fiscal Year]=VALUE(RIGHT(G$1,4))),Table1[Value],"Not found"))} -> 11148 | H3: {=IF($A3="","",_xlfn.XLOOKUP(1,(Table1[Line Item]=$A3)*(Table1[Fiscal Year]=VALUE(RIGHT(H$1,4))),Table1[Value],"Not found"))} -> 12156 | I3: {=IF($A3="","",_xlfn.XLOOKUP(1,(Table1[Line Item]=$A3)*(Table1[Fiscal Year]=VALUE(RIGHT(I$1,4))),Table1[Value],"Not found"))} -> 11142
A4: retail | B4: {=IF($A4="","",_xlfn.XLOOKUP(1,(Table1[Line Item]=$A4)*(Table1[Fiscal Year]=VALUE(RIGHT(B$1,4))),Table1[Value],"Not found"))} -> 5841 | C4: {=IF($A4="","",_xlfn.XLOOKUP(1,(Table1[Line Item]=$A4)*(Table1[Fiscal Year]=VALUE(RIGHT(C$1,4))),Table1[Value],"Not found"))} -> 7172 | D4: {=IF($A4="","",_xlfn.XLOOKUP(1,(Table1[Line Item]=$A4)*(Table1[Fiscal Year]=VALUE(RIGHT(D$1,4))),Table1[Value],"Not found"))} -> 8196 | E4: {=IF($A4="","",_xlfn.XLOOKUP(1,(Table1[Line Item]=$A4)*(Table1[Fiscal Year]=VALUE(RIGHT(E$1,4))),Table1[Value],"Not found"))} -> 9480 | F4: {=IF($A4="","",_xlfn.XLOOKUP(1,(Table1[Line Item]=$A4)*(Table1[Fiscal Year]=VALUE(RIGHT(F$1,4))),Table1[Value],"Not found"))} -> 8970 | G4: {=IF($A4="","",_xlfn.XLOOKUP(1,(Table1[Line Item]=$A4)*(Table1[Fiscal Year]=VALUE(RIGHT(G$1,4))),Table1[Value],"Not found"))} -> 9428 | H4: {=IF($A4="","",_xlfn.XLOOKUP(1,(Table1[Line Item]=$A4)*(Table1[Fiscal Year]=VALUE(RIGHT(H$1,4))),Table1[Value],"Not found"))} -> 9725 | I4: {=IF($A4="","",_xlfn.XLOOKUP(1,(Table1[Line Item]=$A4)*(Table1[Fiscal Year]=VALUE(RIGHT(I$1,4))),Table1[Value],"Not found"))} -> 9706
A5: other businesses | B5: {=IF($A5="","",_xlfn.XLOOKUP(1,(Table1[Line Item]=$A5)*(Table1[Fiscal Year]=VALUE(RIGHT(B$1,4))),Table1[Value],"Not found"))} -> 979 | C5: {=IF($A5="","",_xlfn.XLOOKUP(1,(Table1[Line Item]=$A5)*(Table1[Fiscal Year]=VALUE(RIGHT(C$1,4))),Table1[Value],"Not found"))} -> 1103 | D5: {=IF($A5="","",_xlfn.XLOOKUP(1,(Table1[Line Item]=$A5)*(Table1[Fiscal Year]=VALUE(RIGHT(D$1,4))),Table1[Value],"Not found"))} -> 986 | E5: {=IF($A5="","",_xlfn.XLOOKUP(1,(Table1[Line Item]=$A5)*(Table1[Fiscal Year]=VALUE(RIGHT(E$1,4))),Table1[Value],"Not found"))} -> 969 | F5: {=IF($A5="","",_xlfn.XLOOKUP(1,(Table1[Line Item]=$A5)*(Table1[Fiscal Year]=VALUE(RIGHT(F$1,4))),Table1[Value],"Not found"))} -> 714 | G5: {=IF($A5="","",_xlfn.XLOOKUP(1,(Table1[Line Item]=$A5)*(Table1[Fiscal Year]=VALUE(RIGHT(G$1,4))),Table1[Value],"Not found"))} -> 658 | H5: {=IF($A5="","",_xlfn.XLOOKUP(1,(Table1[Line Item]=$A5)*(Table1[Fiscal Year]=VALUE(RIGHT(H$1,4))),Table1[Value],"Not found"))} -> 630 | I5: {=IF($A5="","",_xlfn.XLOOKUP(1,(Table1[Line Item]=$A5)*(Table1[Fiscal Year]=VALUE(RIGHT(I$1,4))),Table1[Value],"Not found"))} -> 579
A6: total net revenue | B6: {=IF($A6="","",_xlfn.XLOOKUP(1,(Table1[Line Item]=$A6)*(Table1[Fiscal Year]=VALUE(RIGHT(B$1,4))),Table1[Value],"Not found"))} -> 18483 | C6: {=IF($A6="","",_xlfn.XLOOKUP(1,(Table1[Line Item]=$A6)*(Table1[Fiscal Year]=VALUE(RIGHT(C$1,4))),Table1[Value],"Not found"))} -> 21218 | D6: {=IF($A6="","",_xlfn.XLOOKUP(1,(Table1[Line Item]=$A6)*(Table1[Fiscal Year]=VALUE(RIGHT(D$1,4))),Table1[Value],"Not found"))} -> 21915 | E6: {=IF($A6="","",_xlfn.XLOOKUP(1,(Table1[Line Item]=$A6)*(Table1[Fiscal Year]=VALUE(RIGHT(E$1,4))),Table1[Value],"Not found"))} -> 23640 | F6: {=IF($A6="","",_xlfn.XLOOKUP(1,(Table1[Line Item]=$A6)*(Table1[Fiscal Year]=VALUE(RIGHT(F$1,4))),Table1[Value],"Not found"))} -> 19844 | G6: {=IF($A6="","",_xlfn.XLOOKUP(1,(Table1[Line Item]=$A6)*(Table1[Fiscal Year]=VALUE(RIGHT(G$1,4))),Table1[Value],"Not found"))} -> 21234 | H6: {=IF($A6="","",_xlfn.XLOOKUP(1,(Table1[Line Item]=$A6)*(Table1[Fiscal Year]=VALUE(RIGHT(H$1,4))),Table1[Value],"Not found"))} -> 22511 | I6: {=IF($A6="","",_xlfn.XLOOKUP(1,(Table1[Line Item]=$A6)*(Table1[Fiscal Year]=VALUE(RIGHT(I$1,4))),Table1[Value],"Not found"))} -> 21427
A7: revenue growth y/y | B7: {=IF($A7="","",_xlfn.XLOOKUP(1,(Table1[Line Item]=$A7)*(Table1[Fiscal Year]=VALUE(RIGHT(B$1,4))),Table1[Value],"Not found"))} -> 0 | C7: {=IF($A7="","",_xlfn.XLOOKUP(1,(Table1[Line Item]=$A7)*(Table1[Fiscal Year]=VALUE(RIGHT(C$1,4))),Table1[Value],"Not found"))} -> 0.148 | D7: {=IF($A7="","",_xlfn.XLOOKUP(1,(Table1[Line Item]=$A7)*(Table1[Fiscal Year]=VALUE(RIGHT(D$1,4))),Table1[Value],"Not found"))} -> 0.033 | E7: {=IF($A7="","",_xlfn.XLOOKUP(1,(Table1[Line Item]=$A7)*(Table1[Fiscal Year]=VALUE(RIGHT(E$1,4))),Table1[Value],"Not found"))} -> 0.079 | F7: {=IF($A7="","",_xlfn.XLOOKUP(1,(Table1[Line Item]=$A7)*(Table1[Fiscal Year]=VALUE(RIGHT(F$1,4))),Table1[Value],"Not found"))} -> -0.161 | G7: {=IF($A7="","",_xlfn.XLOOKUP(1,(Table1[Line Item]=$A7)*(Table1[Fiscal Year]=VALUE(RIGHT(G$1,4))),Table1[Value],"Not found"))} -> 0.07 | H7: {=IF($A7="","",_xlfn.XLOOKUP(1,(Table1[Line Item]=$A7)*(Table1[Fiscal Year]=VALUE(RIGHT(H$1,4))),Table1[Value],"Not found"))} -> 0.06 | I7: {=IF($A7="","",_xlfn.XLOOKUP(1,(Table1[Line Item]=$A7)*(Table1[Fiscal Year]=VALUE(RIGHT(I$1,4))),Table1[Value],"Not found"))} -> -0.048
B8: {=IF($A8="","",_xlfn.XLOOKUP(1,(Table1[Line Item]=$A8)*(Table1[Fiscal Year]=VALUE(RIGHT(B$1,4))),Table1[Value],"Not found"))} | C8: {=IF($A8="","",_xlfn.XLOOKUP(1,(Table1[Line Item]=$A8)*(Table1[Fiscal Year]=VALUE(RIGHT(C$1,4))),Table1[Value],"Not found"))} | D8: {=IF($A8="","",_xlfn.XLOOKUP(1,(Table1[Line Item]=$A8)*(Table1[Fiscal Year]=VALUE(RIGHT(D$1,4))),Table1[Value],"Not found"))} | E8: {=IF($A8="","",_xlfn.XLOOKUP(1,(Table1[Line Item]=$A8)*(Table1[Fiscal Year]=VALUE(RIGHT(E$1,4))),Table1[Value],"Not found"))} | F8: {=IF($A8="","",_xlfn.XLOOKUP(1,(Table1[Line Item]=$A8)*(Table1[Fiscal Year]=VALUE(RIGHT(F$1,4))),Table1[Value],"Not found"))} | G8: {=IF($A8="","",_xlfn.XLOOKUP(1,(Table1[Line Item]=$A8)*(Table1[Fiscal Year]=VALUE(RIGHT(G$1,4))),Table1[Value],"Not found"))} | H8: {=IF($A8="","",_xlfn.XLOOKUP(1,(Table1[Line Item]=$A8)*(Table1[Fiscal Year]=VALUE(RIGHT(H$1,4))),Table1[Value],"Not found"))} | I8: {=IF($A8="","",_xlfn.XLOOKUP(1,(Table1[Line Item]=$A8)*(Table1[Fiscal Year]=VALUE(RIGHT(I$1,4))),Table1[Value],"Not found"))}
A9: cost of goods sold | B9: {=IF($A9="","",_xlfn.XLOOKUP(1,(Table1[Line Item]=$A9)*(Table1[Fiscal Year]=VALUE(RIGHT(B$1,4))),Table1[Value],"Not found"))} -> -9500 | C9: {=IF($A9="","",_xlfn.XLOOKUP(1,(Table1[Line Item]=$A9)*(Table1[Fiscal Year]=VALUE(RIGHT(C$1,4))),Table1[Value],"Not found"))} -> -10524 | D9: {=IF($A9="","",_xlfn.XLOOKUP(1,(Table1[Line Item]=$A9)*(Table1[Fiscal Year]=VALUE(RIGHT(D$1,4))),Table1[Value],"Not found"))} -> -10607 | E9: {=IF($A9="","",_xlfn.XLOOKUP(1,(Table1[Line Item]=$A9)*(Table1[Fiscal Year]=VALUE(RIGHT(E$1,4))),Table1[Value],"Not found"))} -> -11347 | F9: {=IF($A9="","",_xlfn.XLOOKUP(1,(Table1[Line Item]=$A9)*(Table1[Fiscal Year]=VALUE(RIGHT(F$1,4))),Table1[Value],"Not found"))} -> -9982 | G9: {=IF($A9="","",_xlfn.XLOOKUP(1,(Table1[Line Item]=$A9)*(Table1[Fiscal Year]=VALUE(RIGHT(G$1,4))),Table1[Value],"Not found"))} -> -10511 | H9: {=IF($A9="","",_xlfn.XLOOKUP(1,(Table1[Line Item]=$A9)*(Table1[Fiscal Year]=VALUE(RIGHT(H$1,4))),Table1[Value],"Not found"))} -> -11863 | I9: {=IF($A9="","",_xlfn.XLOOKUP(1,(Table1[Line Item]=$A9)*(Table1[Fiscal Year]=VALUE(RIGHT(I$1,4))),Table1[Value],"Not found"))} -> -11249
A10: gross profit | B10: {=IF($A10="","",_xlfn.XLOOKUP(1,(Table1[Line Item]=$A10)*(Table1[Fiscal Year]=VALUE(RIGHT(B$1,4))),Table1[Value],"Not found"))} -> 8983 | C10: {=IF($A10="","",_xlfn.XLOOKUP(1,(Table1[Line Item]=$A10)*(Table1[Fiscal Year]=VALUE(RIGHT(C$1,4))),Table1[Value],"Not found"))} -> 10694 | D10: {=IF($A10="","",_xlfn.XLOOKUP(1,(Table1[Line Item]=$A10)*(Table1[Fiscal Year]=VALUE(RIGHT(D$1,4))),Table1[Value],"Not found"))} -> 11308 | E10: {=IF($A10="","",_xlfn.XLOOKUP(1,(Table1[Line Item]=$A10)*(Table1[Fiscal Year]=VALUE(RIGHT(E$1,4))),Table1[Value],"Not found"))} -> 12293 | F10: {=IF($A10="","",_xlfn.XLOOKUP(1,(Table1[Line Item]=$A10)*(Table1[Fiscal Year]=VALUE(RIGHT(F$1,4))),Table1[Value],"Not found"))} -> 9862 | G10: {=IF($A10="","",_xlfn.XLOOKUP(1,(Table1[Line Item]=$A10)*(Table1[Fiscal Year]=VALUE(RIGHT(G$1,4))),Table1[Value],"Not found"))} -> 10723 | H10: {=IF($A10="","",_xlfn.XLOOKUP(1,(Table1[Line Item]=$A10)*(Table1[Fiscal Year]=VALUE(RIGHT(H$1,4))),Table1[Value],"Not found"))} -> 10648 | I10: {=IF($A10="","",_xlfn.XLOOKUP(1,(Table1[Line Item]=$A10)*(Table1[Fiscal Year]=VALUE(RIGHT(I$1,4))),Table1[Value],"Not found"))} -> 10178
A11: gross margin % | B11: {=IF($A11="","",_xlfn.XLOOKUP(1,(Table1[Line Item]=$A11)*(Table1[Fiscal Year]=VALUE(RIGHT(B$1,4))),Table1[Value],"Not found"))} -> 0.486 | C11: {=IF($A11="","",_xlfn.XLOOKUP(1,(Table1[Line Item]=$A11)*(Table1[Fiscal Year]=VALUE(RIGHT(C$1,4))),Table1[Value],"Not found"))} -> 0.504 | D11: {=IF($A11="","",_xlfn.XLOOKUP(1,(Table1[Line Item]=$A11)*(Table1[Fiscal Year]=VALUE(RIGHT(D$1,4))),Table1[Value],"Not found"))} -> 0.516 | E11: {=IF($A11="","",_xlfn.XLOOKUP(1,(Table1[Line Item]=$A11)*(Table1[Fiscal Year]=VALUE(RIGHT(E$1,4))),Table1[Value],"Not found"))} -> 0.52 | F11: {=IF($A11="","",_xlfn.XLOOKUP(1,(Table1[Line Item]=$A11)*(Table1[Fiscal Year]=VALUE(RIGHT(F$1,4))),Table1[Value],"Not found"))} -> 0.497 | G11: {=IF($A11="","",_xlfn.XLOOKUP(1,(Table1[Line Item]=$A11)*(Table1[Fiscal Year]=VALUE(RIGHT(G$1,4))),Table1[Value],"Not found"))} -> 0.505 | H11: {=IF($A11="","",_xlfn.XLOOKUP(1,(Table1[Line Item]=$A11)*(Table1[Fiscal Year]=VALUE(RIGHT(H$1,4))),Table1[Value],"Not found"))} -> 0.473 | I11: {=IF($A11="","",_xlfn.XLOOKUP(1,(Table1[Line Item]=$A11)*(Table1[Fiscal Year]=VALUE(RIGHT(I$1,4))),Table1[Value],"Not found"))} -> 0.475
B12: {=IF($A12="","",_xlfn.XLOOKUP(1,(Table1[Line Item]=$A12)*(Table1[Fiscal Year]=VALUE(RIGHT(B$1,4))),Table1[Value],"Not found"))} | C12: {=IF($A12="","",_xlfn.XLOOKUP(1,(Table1[Line Item]=$A12)*(Table1[Fiscal Year]=VALUE(RIGHT(C$1,4))),Table1[Value],"Not found"))} | D12: {=IF($A12="","",_xlfn.XLOOKUP(1,(Table1[Line Item]=$A12)*(Table1[Fiscal Year]=VALUE(RIGHT(D$1,4))),Table1[Value],"Not found"))} | E12: {=IF($A12="","",_xlfn.XLOOKUP(1,(Table1[Line Item]=$A12)*(Table1[Fiscal Year]=VALUE(RIGHT(E$1,4))),Table1[Value],"Not found"))} | F12: {=IF($A12="","",_xlfn.XLOOKUP(1,(Table1[Line Item]=$A12)*(Table1[Fiscal Year]=VALUE(RIGHT(F$1,4))),Table1[Value],"Not found"))} | G12: {=IF($A12="","",_xlfn.XLOOKUP(1,(Table1[Line Item]=$A12)*(Table1[Fiscal Year]=VALUE(RIGHT(G$1,4))),Table1[Value],"Not found"))} | H12: {=IF($A12="","",_xlfn.XLOOKUP(1,(Table1[Line Item]=$A12)*(Table1[Fiscal Year]=VALUE(RIGHT(H$1,4))),Table1[Value],"Not found"))} | I12: {=IF($A12="","",_xlfn.XLOOKUP(1,(Table1[Line Item]=$A12)*(Table1[Fiscal Year]=VALUE(RIGHT(I$1,4))),Table1[Value],"Not found"))}
A13: royalty and commission income | B13: {=IF($A13="","",_xlfn.XLOOKUP(1,(Table1[Line Item]=$A13)*(Table1[Fiscal Year]=VALUE(RIGHT(B$1,4))),Table1[Value],"Not found"))} -> 108 | C13: {=IF($A13="","",_xlfn.XLOOKUP(1,(Table1[Line Item]=$A13)*(Table1[Fiscal Year]=VALUE(RIGHT(C$1,4))),Table1[Value],"Not found"))} -> 115 | D13: {=IF($A13="","",_xlfn.XLOOKUP(1,(Table1[Line Item]=$A13)*(Table1[Fiscal Year]=VALUE(RIGHT(D$1,4))),Table1[Value],"Not found"))} -> 121 | E13: {=IF($A13="","",_xlfn.XLOOKUP(1,(Table1[Line Item]=$A13)*(Table1[Fiscal Year]=VALUE(RIGHT(E$1,4))),Table1[Value],"Not found"))} -> 130 | F13: {=IF($A13="","",_xlfn.XLOOKUP(1,(Table1[Line Item]=$A13)*(Table1[Fiscal Year]=VALUE(RIGHT(F$1,4))),Table1[Value],"Not found"))} -> 96 | G13: {=IF($A13="","",_xlfn.XLOOKUP(1,(Table1[Line Item]=$A13)*(Table1[Fiscal Year]=VALUE(RIGHT(G$1,4))),Table1[Value],"Not found"))} -> 104 | H13: {=IF($A13="","",_xlfn.XLOOKUP(1,(Table1[Line Item]=$A13)*(Table1[Fiscal Year]=VALUE(RIGHT(H$1,4))),Table1[Value],"Not found"))} -> 112 | I13: {=IF($A13="","",_xlfn.XLOOKUP(1,(Table1[Line Item]=$A13)*(Table1[Fiscal Year]=VALUE(RIGHT(I$1,4))),Table1[Value],"Not found"))} -> 107
A14: other operating income | B14: {=IF($A14="","",_xlfn.XLOOKUP(1,(Table1[Line Item]=$A14)*(Table1[Fiscal Year]=VALUE(RIGHT(B$1,4))),Table1[Value],"Not found"))} -> 60 | C14: {=IF($A14="","",_xlfn.XLOOKUP(1,(Table1[Line Item]=$A14)*(Table1[Fiscal Year]=VALUE(RIGHT(C$1,4))),Table1[Value],"Not found"))} -> 66 | D14: {=IF($A14="","",_xlfn.XLOOKUP(1,(Table1[Line Item]=$A14)*(Table1[Fiscal Year]=VALUE(RIGHT(D$1,4))),Table1[Value],"Not found"))} -> 71 | E14: {=IF($A14="","",_xlfn.XLOOKUP(1,(Table1[Line Item]=$A14)*(Table1[Fiscal Year]=VALUE(RIGHT(E$1,4))),Table1[Value],"Not found"))} -> 78 | F14: {=IF($A14="","",_xlfn.XLOOKUP(1,(Table1[Line Item]=$A14)*(Table1[Fiscal Year]=VALUE(RIGHT(F$1,4))),Table1[Value],"Not found"))} -> 52 | G14: {=IF($A14="","",_xlfn.XLOOKUP(1,(Table1[Line Item]=$A14)*(Table1[Fiscal Year]=VALUE(RIGHT(G$1,4))),Table1[Value],"Not found"))} -> 58 | H14: {=IF($A14="","",_xlfn.XLOOKUP(1,(Table1[Line Item]=$A14)*(Table1[Fiscal Year]=VALUE(RIGHT(H$1,4))),Table1[Value],"Not found"))} -> 63 | I14: {=IF($A14="","",_xlfn.XLOOKUP(1,(Table1[Line Item]=$A14)*(Table1[Fiscal Year]=VALUE(RIGHT(I$1,4))),Table1[Value],"Not found"))} -> 55
A15: marketing and point-of-sale | B15: {=IF($A15="","",_xlfn.XLOOKUP(1,(Table1[Line Item]=$A15)*(Table1[Fiscal Year]=VALUE(RIGHT(B$1,4))),Table1[Value],"Not found"))} -> -2532 | C15: {=IF($A15="","",_xlfn.XLOOKUP(1,(Table1[Line Item]=$A15)*(Table1[Fiscal Year]=VALUE(RIGHT(C$1,4))),Table1[Value],"Not found"))} -> -2843 | D15: {=IF($A15="","",_xlfn.XLOOKUP(1,(Table1[Line Item]=$A15)*(Table1[Fiscal Year]=VALUE(RIGHT(D$1,4))),Table1[Value],"Not found"))} -> -2871 | E15: {=IF($A15="","",_xlfn.XLOOKUP(1,(Table1[Line Item]=$A15)*(Table1[Fiscal Year]=VALUE(RIGHT(E$1,4))),Table1[Value],"Not found"))} -> -3026 | F15: {=IF($A15="","",_xlfn.XLOOKUP(1,(Table1[Line Item]=$A15)*(Table1[Fiscal Year]=VALUE(RIGHT(F$1,4))),Table1[Value],"Not found"))} -> -2361 | G15: {=IF($A15="","",_xlfn.XLOOKUP(1,(Table1[Line Item]=$A15)*(Table1[Fiscal Year]=VALUE(RIGHT(G$1,4))),Table1[Value],"Not found"))} -> -2569 | H15: {=IF($A15="","",_xlfn.XLOOKUP(1,(Table1[Line Item]=$A15)*(Table1[Fiscal Year]=VALUE(RIGHT(H$1,4))),Table1[Value],"Not found"))} -> -2791 | I15: {=IF($A15="","",_xlfn.XLOOKUP(1,(Table1[Line Item]=$A15)*(Table1[Fiscal Year]=VALUE(RIGHT(I$1,4))),Table1[Value],"Not found"))} -> -2636
A16: distribution and selling expense | B16: {=IF($A16="","",_xlfn.XLOOKUP(1,(Table1[Line Item]=$A16)*(Table1[Fiscal Year]=VALUE(RIGHT(B$1,4))),Table1[Value],"Not found"))} -> -4029 | C16: {=IF($A16="","",_xlfn.XLOOKUP(1,(Table1[Line Item]=$A16)*(Table1[Fiscal Year]=VALUE(RIGHT(C$1,4))),Table1[Value],"Not found"))} -> -4710 | D16: {=IF($A16="","",_xlfn.XLOOKUP(1,(Table1[Line Item]=$A16)*(Table1[Fiscal Year]=VALUE(RIGHT(D$1,4))),Table1[Value],"Not found"))} -> -4909 | E16: {=IF($A16="","",_xlfn.XLOOKUP(1,(Table1[Line Item]=$A16)*(Table1[Fiscal Year]=VALUE(RIGHT(E$1,4))),Table1[Value],"Not found"))} -> -5272 | F16: {=IF($A16="","",_xlfn.XLOOKUP(1,(Table1[Line Item]=$A16)*(Table1[Fiscal Year]=VALUE(RIGHT(F$1,4))),Table1[Value],"Not found"))} -> -5358 | G16: {=IF($A16="","",_xlfn.XLOOKUP(1,(Table1[Line Item]=$A16)*(Table1[Fiscal Year]=VALUE(RIGHT(G$1,4))),Table1[Value],"Not found"))} -> -4969 | H16: {=IF($A16="","",_xlfn.XLOOKUP(1,(Table1[Line Item]=$A16)*(Table1[Fiscal Year]=VALUE(RIGHT(H$1,4))),Table1[Value],"Not found"))} -> -5470 | I16: {=IF($A16="","",_xlfn.XLOOKUP(1,(Table1[Line Item]=$A16)*(Table1[Fiscal Year]=VALUE(RIGHT(I$1,4))),Table1[Value],"Not found"))} -> -5528
A17: general & administration | B17: {=IF($A17="","",_xlfn.XLOOKUP(1,(Table1[Line Item]=$A17)*(Table1[Fiscal Year]=VALUE(RIGHT(B$1,4))),Table1[Value],"Not found"))} -> -998 | C17: {=IF($A17="","",_xlfn.XLOOKUP(1,(Table1[Line Item]=$A17)*(Table1[Fiscal Year]=VALUE(RIGHT(C$1,4))),Table1[Value],"Not found"))} -> -1125 | D17: {=IF($A17="","",_xlfn.XLOOKUP(1,(Table1[Line Item]=$A17)*(Table1[Fiscal Year]=VALUE(RIGHT(D$1,4))),Table1[Value],"Not found"))} -> -1140 | E17: {=IF($A17="","",_xlfn.XLOOKUP(1,(Table1[Line Item]=$A17)*(Table1[Fiscal Year]=VALUE(RIGHT(E$1,4))),Table1[Value],"Not found"))} -> -1347 | F17: {=IF($A17="","",_xlfn.XLOOKUP(1,(Table1[Line Item]=$A17)*(Table1[Fiscal Year]=VALUE(RIGHT(F$1,4))),Table1[Value],"Not found"))} -> -1290 | G17: {=IF($A17="","",_xlfn.XLOOKUP(1,(Table1[Line Item]=$A17)*(Table1[Fiscal Year]=VALUE(RIGHT(G$1,4))),Table1[Value],"Not found"))} -> -1295 | H17: {=IF($A17="","",_xlfn.XLOOKUP(1,(Table1[Line Item]=$A17)*(Table1[Fiscal Year]=VALUE(RIGHT(H$1,4))),Table1[Value],"Not found"))} -> -1756 | I17: {=IF($A17="","",_xlfn.XLOOKUP(1,(Table1[Line Item]=$A17)*(Table1[Fiscal Year]=VALUE(RIGHT(I$1,4))),Table1[Value],"Not found"))} -> -1564
A18: sundry expenses | B18: {=IF($A18="","",_xlfn.XLOOKUP(1,(Table1[Line Item]=$A18)*(Table1[Fiscal Year]=VALUE(RIGHT(B$1,4))),Table1[Value],"Not found"))} -> -185 | C18: {=IF($A18="","",_xlfn.XLOOKUP(1,(Table1[Line Item]=$A18)*(Table1[Fiscal Year]=VALUE(RIGHT(C$1,4))),Table1[Value],"Not found"))} -> -212 | D18: {=IF($A18="","",_xlfn.XLOOKUP(1,(Table1[Line Item]=$A18)*(Table1[Fiscal Year]=VALUE(RIGHT(D$1,4))),Table1[Value],"Not found"))} -> -219 | E18: {=IF($A18="","",_xlfn.XLOOKUP(1,(Table1[Line Item]=$A18)*(Table1[Fiscal Year]=VALUE(RIGHT(E$1,4))),Table1[Value],"Not found"))} -> -236 | F18: {=IF($A18="","",_xlfn.XLOOKUP(1,(Table1[Line Item]=$A18)*(Table1[Fiscal Year]=VALUE(RIGHT(F$1,4))),Table1[Value],"Not found"))} -> -198 | G18: {=IF($A18="","",_xlfn.XLOOKUP(1,(Table1[Line Item]=$A18)*(Table1[Fiscal Year]=VALUE(RIGHT(G$1,4))),Table1[Value],"Not found"))} -> -212 | H18: {=IF($A18="","",_xlfn.XLOOKUP(1,(Table1[Line Item]=$A18)*(Table1[Fiscal Year]=VALUE(RIGHT(H$1,4))),Table1[Value],"Not found"))} -> -225 | I18: {=IF($A18="","",_xlfn.XLOOKUP(1,(Table1[Line Item]=$A18)*(Table1[Fiscal Year]=VALUE(RIGHT(I$1,4))),Table1[Value],"Not found"))} -> -257
A19: total other operating exp. | B19: {=IF($A19="","",_xlfn.XLOOKUP(1,(Table1[Line Item]=$A19)*(Table1[Fiscal Year]=VALUE(RIGHT(B$1,4))),Table1[Value],"Not found"))} -> -7744 | C19: {=IF($A19="","",_xlfn.XLOOKUP(1,(Table1[Line Item]=$A19)*(Table1[Fiscal Year]=VALUE(RIGHT(C$1,4))),Table1[Value],"Not found"))} -> -8890 | D19: {=IF($A19="","",_xlfn.XLOOKUP(1,(Table1[Line Item]=$A19)*(Table1[Fiscal Year]=VALUE(RIGHT(D$1,4))),Table1[Value],"Not found"))} -> -9139 | E19: {=IF($A19="","",_xlfn.XLOOKUP(1,(Table1[Line Item]=$A19)*(Table1[Fiscal Year]=VALUE(RIGHT(E$1,4))),Table1[Value],"Not found"))} -> -9881 | F19: {=IF($A19="","",_xlfn.XLOOKUP(1,(Table1[Line Item]=$A19)*(Table1[Fiscal Year]=VALUE(RIGHT(F$1,4))),Table1[Value],"Not found"))} -> -9207 | G19: {=IF($A19="","",_xlfn.XLOOKUP(1,(Table1[Line Item]=$A19)*(Table1[Fiscal Year]=VALUE(RIGHT(G$1,4))),Table1[Value],"Not found"))} -> -9045 | H19: {=IF($A19="","",_xlfn.XLOOKUP(1,(Table1[Line Item]=$A19)*(Table1[Fiscal Year]=VALUE(RIGHT(H$1,4))),Table1[Value],"Not found"))} -> -10242 | I19: {=IF($A19="","",_xlfn.XLOOKUP(1,(Table1[Line Item]=$A19)*(Table1[Fiscal Year]=VALUE(RIGHT(I$1,4))),Table1[Value],"Not found"))} -> -9985
A20: goodwill / intangible impairment | B20: {=IF($A20="","",_xlfn.XLOOKUP(1,(Table1[Line Item]=$A20)*(Table1[Fiscal Year]=VALUE(RIGHT(B$1,4))),Table1[Value],"Not found"))} -> 0 | C20: {=IF($A20="","",_xlfn.XLOOKUP(1,(Table1[Line Item]=$A20)*(Table1[Fiscal Year]=VALUE(RIGHT(C$1,4))),Table1[Value],"Not found"))} -> 0 | D20: {=IF($A20="","",_xlfn.XLOOKUP(1,(Table1[Line Item]=$A20)*(Table1[Fiscal Year]=VALUE(RIGHT(D$1,4))),Table1[Value],"Not found"))} -> 0 | E20: {=IF($A20="","",_xlfn.XLOOKUP(1,(Table1[Line Item]=$A20)*(Table1[Fiscal Year]=VALUE(RIGHT(E$1,4))),Table1[Value],"Not found"))} -> 0 | F20: {=IF($A20="","",_xlfn.XLOOKUP(1,(Table1[Line Item]=$A20)*(Table1[Fiscal Year]=VALUE(RIGHT(F$1,4))),Table1[Value],"Not found"))} -> 0 | G20: {=IF($A20="","",_xlfn.XLOOKUP(1,(Table1[Line Item]=$A20)*(Table1[Fiscal Year]=VALUE(RIGHT(G$1,4))),Table1[Value],"Not found"))} -> 0 | H20: {=IF($A20="","",_xlfn.XLOOKUP(1,(Table1[Line Item]=$A20)*(Table1[Fiscal Year]=VALUE(RIGHT(H$1,4))),Table1[Value],"Not found"))} -> -194 | I20: {=IF($A20="","",_xlfn.XLOOKUP(1,(Table1[Line Item]=$A20)*(Table1[Fiscal Year]=VALUE(RIGHT(I$1,4))),Table1[Value],"Not found"))} -> 0
B21: {=IF($A21="","",_xlfn.XLOOKUP(1,(Table1[Line Item]=$A21)*(Table1[Fiscal Year]=VALUE(RIGHT(B$1,4))),Table1[Value],"Not found"))} | C21: {=IF($A21="","",_xlfn.XLOOKUP(1,(Table1[Line Item]=$A21)*(Table1[Fiscal Year]=VALUE(RIGHT(C$1,4))),Table1[Value],"Not found"))} | D21: {=IF($A21="","",_xlfn.XLOOKUP(1,(Table1[Line Item]=$A21)*(Table1[Fiscal Year]=VALUE(RIGHT(D$1,4))),Table1[Value],"Not found"))} | E21: {=IF($A21="","",_xlfn.XLOOKUP(1,(Table1[Line Item]=$A21)*(Table1[Fiscal Year]=VALUE(RIGHT(E$1,4))),Table1[Value],"Not found"))} | F21: {=IF($A21="","",_xlfn.XLOOKUP(1,(Table1[Line Item]=$A21)*(Table1[Fiscal Year]=VALUE(RIGHT(F$1,4))),Table1[Value],"Not found"))} | G21: {=IF($A21="","",_xlfn.XLOOKUP(1,(Table1[Line Item]=$A21)*(Table1[Fiscal Year]=VALUE(RIGHT(G$1,4))),Table1[Value],"Not found"))} | H21: {=IF($A21="","",_xlfn.XLOOKUP(1,(Table1[Line Item]=$A21)*(Table1[Fiscal Year]=VALUE(RIGHT(H$1,4))),Table1[Value],"Not found"))} | I21: {=IF($A21="","",_xlfn.XLOOKUP(1,(Table1[Line Item]=$A21)*(Table1[Fiscal Year]=VALUE(RIGHT(I$1,4))),Table1[Value],"Not found"))}
A22: operating profit (ebit) | B22: {=IF($A22="","",_xlfn.XLOOKUP(1,(Table1[Line Item]=$A22)*(Table1[Fiscal Year]=VALUE(RIGHT(B$1,4))),Table1[Value],"Not found"))} -> 1407 | C22: {=IF($A22="","",_xlfn.XLOOKUP(1,(Table1[Line Item]=$A22)*(Table1[Fiscal Year]=VALUE(RIGHT(C$1,4))),Table1[Value],"Not found"))} -> 1985 | D22: {=IF($A22="","",_xlfn.XLOOKUP(1,(Table1[Line Item]=$A22)*(Table1[Fiscal Year]=VALUE(RIGHT(D$1,4))),Table1[Value],"Not found"))} -> 2361 | E22: {=IF($A22="","",_xlfn.XLOOKUP(1,(Table1[Line Item]=$A22)*(Table1[Fiscal Year]=VALUE(RIGHT(E$1,4))),Table1[Value],"Not found"))} -> 2620 | F22: {=IF($A22="","",_xlfn.XLOOKUP(1,(Table1[Line Item]=$A22)*(Table1[Fiscal Year]=VALUE(RIGHT(F$1,4))),Table1[Value],"Not found"))} -> 803 | G22: {=IF($A22="","",_xlfn.XLOOKUP(1,(Table1[Line Item]=$A22)*(Table1[Fiscal Year]=VALUE(RIGHT(G$1,4))),Table1[Value],"Not found"))} -> 1840 | H22: {=IF($A22="","",_xlfn.XLOOKUP(1,(Table1[Line Item]=$A22)*(Table1[Fiscal Year]=VALUE(RIGHT(H$1,4))),Table1[Value],"Not found"))} -> 387 | I22: {=IF($A22="","",_xlfn.XLOOKUP(1,(Table1[Line Item]=$A22)*(Table1[Fiscal Year]=VALUE(RIGHT(I$1,4))),Table1[Value],"Not found"))} -> 355
A23: operating margin % | B23: {=IF($A23="","",_xlfn.XLOOKUP(1,(Table1[Line Item]=$A23)*(Table1[Fiscal Year]=VALUE(RIGHT(B$1,4))),Table1[Value],"Not found"))} -> 0.076 | C23: {=IF($A23="","",_xlfn.XLOOKUP(1,(Table1[Line Item]=$A23)*(Table1[Fiscal Year]=VALUE(RIGHT(C$1,4))),Table1[Value],"Not found"))} -> 0.094 | D23: {=IF($A23="","",_xlfn.XLOOKUP(1,(Table1[Line Item]=$A23)*(Table1[Fiscal Year]=VALUE(RIGHT(D$1,4))),Table1[Value],"Not found"))} -> 0.108 | E23: {=IF($A23="","",_xlfn.XLOOKUP(1,(Table1[Line Item]=$A23)*(Table1[Fiscal Year]=VALUE(RIGHT(E$1,4))),Table1[Value],"Not found"))} -> 0.111 | F23: {=IF($A23="","",_xlfn.XLOOKUP(1,(Table1[Line Item]=$A23)*(Table1[Fiscal Year]=VALUE(RIGHT(F$1,4))),Table1[Value],"Not found"))} -> 0.04 | G23: {=IF($A23="","",_xlfn.XLOOKUP(1,(Table1[Line Item]=$A23)*(Table1[Fiscal Year]=VALUE(RIGHT(G$1,4))),Table1[Value],"Not found"))} -> 0.087 | H23: {=IF($A23="","",_xlfn.XLOOKUP(1,(Table1[Line Item]=$A23)*(Table1[Fiscal Year]=VALUE(RIGHT(H$1,4))),Table1[Value],"Not found"))} -> 0.017 | I23: {=IF($A23="","",_xlfn.XLOOKUP(1,(Table1[Line Item]=$A23)*(Table1[Fiscal Year]=VALUE(RIGHT(I$1,4))),Table1[Value],"Not found"))} -> 0.017
B24: {=IF($A24="","",_xlfn.XLOOKUP(1,(Table1[Line Item]=$A24)*(Table1[Fiscal Year]=VALUE(RIGHT(B$1,4))),Table1[Value],"Not found"))} | C24: {=IF($A24="","",_xlfn.XLOOKUP(1,(Table1[Line Item]=$A24)*(Table1[Fiscal Year]=VALUE(RIGHT(C$1,4))),Table1[Value],"Not found"))} | D24: {=IF($A24="","",_xlfn.XLOOKUP(1,(Table1[Line Item]=$A24)*(Table1[Fiscal Year]=VALUE(RIGHT(D$1,4))),Table1[Value],"Not found"))} | E24: {=IF($A24="","",_xlfn.XLOOKUP(1,(Table1[Line Item]=$A24)*(Table1[Fiscal Year]=VALUE(RIGHT(E$1,4))),Table1[Value],"Not found"))} | F24: {=IF($A24="","",_xlfn.XLOOKUP(1,(Table1[Line Item]=$A24)*(Table1[Fiscal Year]=VALUE(RIGHT(F$1,4))),Table1[Value],"Not found"))} | G24: {=IF($A24="","",_xlfn.XLOOKUP(1,(Table1[Line Item]=$A24)*(Table1[Fiscal Year]=VALUE(RIGHT(G$1,4))),Table1[Value],"Not found"))} | H24: {=IF($A24="","",_xlfn.XLOOKUP(1,(Table1[Line Item]=$A24)*(Table1[Fiscal Year]=VALUE(RIGHT(H$1,4))),Table1[Value],"Not found"))} | I24: {=IF($A24="","",_xlfn.XLOOKUP(1,(Table1[Line Item]=$A24)*(Table1[Fiscal Year]=VALUE(RIGHT(I$1,4))),Table1[Value],"Not found"))}
A25: financial income | B25: {=IF($A25="","",_xlfn.XLOOKUP(1,(Table1[Line Item]=$A25)*(Table1[Fiscal Year]=VALUE(RIGHT(B$1,4))),Table1[Value],"Not found"))} -> 20 | C25: {=IF($A25="","",_xlfn.XLOOKUP(1,(Table1[Line Item]=$A25)*(Table1[Fiscal Year]=VALUE(RIGHT(C$1,4))),Table1[Value],"Not found"))} -> 24 | D25: {=IF($A25="","",_xlfn.XLOOKUP(1,(Table1[Line Item]=$A25)*(Table1[Fiscal Year]=VALUE(RIGHT(D$1,4))),Table1[Value],"Not found"))} -> 28 | E25: {=IF($A25="","",_xlfn.XLOOKUP(1,(Table1[Line Item]=$A25)*(Table1[Fiscal Year]=VALUE(RIGHT(E$1,4))),Table1[Value],"Not found"))} -> 32 | F25: {=IF($A25="","",_xlfn.XLOOKUP(1,(Table1[Line Item]=$A25)*(Table1[Fiscal Year]=VALUE(RIGHT(F$1,4))),Table1[Value],"Not found"))} -> 26 | G25: {=IF($A25="","",_xlfn.XLOOKUP(1,(Table1[Line Item]=$A25)*(Table1[Fiscal Year]=VALUE(RIGHT(G$1,4))),Table1[Value],"Not found"))} -> 30 | H25: {=IF($A25="","",_xlfn.XLOOKUP(1,(Table1[Line Item]=$A25)*(Table1[Fiscal Year]=VALUE(RIGHT(H$1,4))),Table1[Value],"Not found"))} -> 44 | I25: {=IF($A25="","",_xlfn.XLOOKUP(1,(Table1[Line Item]=$A25)*(Table1[Fiscal Year]=VALUE(RIGHT(I$1,4))),Table1[Value],"Not found"))} -> 62
A26: financial expenses | B26: {=IF($A26="","",_xlfn.XLOOKUP(1,(Table1[Line Item]=$A26)*(Table1[Fiscal Year]=VALUE(RIGHT(B$1,4))),Table1[Value],"Not found"))} -> -74 | C26: {=IF($A26="","",_xlfn.XLOOKUP(1,(Table1[Line Item]=$A26)*(Table1[Fiscal Year]=VALUE(RIGHT(C$1,4))),Table1[Value],"Not found"))} -> -82 | D26: {=IF($A26="","",_xlfn.XLOOKUP(1,(Table1[Line Item]=$A26)*(Table1[Fiscal Year]=VALUE(RIGHT(D$1,4))),Table1[Value],"Not found"))} -> -91 | E26: {=IF($A26="","",_xlfn.XLOOKUP(1,(Table1[Line Item]=$A26)*(Table1[Fiscal Year]=VALUE(RIGHT(E$1,4))),Table1[Value],"Not found"))} -> -166 | F26: {=IF($A26="","",_xlfn.XLOOKUP(1,(Table1[Line Item]=$A26)*(Table1[Fiscal Year]=VALUE(RIGHT(F$1,4))),Table1[Value],"Not found"))} -> -178 | G26: {=IF($A26="","",_xlfn.XLOOKUP(1,(Table1[Line Item]=$A26)*(Table1[Fiscal Year]=VALUE(RIGHT(G$1,4))),Table1[Value],"Not found"))} -> -172 | H26: {=IF($A26="","",_xlfn.XLOOKUP(1,(Table1[Line Item]=$A26)*(Table1[Fiscal Year]=VALUE(RIGHT(H$1,4))),Table1[Value],"Not found"))} -> -199 | I26: {=IF($A26="","",_xlfn.XLOOKUP(1,(Table1[Line Item]=$A26)*(Table1[Fiscal Year]=VALUE(RIGHT(I$1,4))),Table1[Value],"Not found"))} -> -242
A27: income before taxes | B27: {=IF($A27="","",_xlfn.XLOOKUP(1,(Table1[Line Item]=$A27)*(Table1[Fiscal Year]=VALUE(RIGHT(B$1,4))),Table1[Value],"Not found"))} -> 1353 | C27: {=IF($A27="","",_xlfn.XLOOKUP(1,(Table1[Line Item]=$A27)*(Table1[Fiscal Year]=VALUE(RIGHT(C$1,4))),Table1[Value],"Not found"))} -> 1927 | D27: {=IF($A27="","",_xlfn.XLOOKUP(1,(Table1[Line Item]=$A27)*(Table1[Fiscal Year]=VALUE(RIGHT(D$1,4))),Table1[Value],"Not found"))} -> 2298 | E27: {=IF($A27="","",_xlfn.XLOOKUP(1,(Table1[Line Item]=$A27)*(Table1[Fiscal Year]=VALUE(RIGHT(E$1,4))),Table1[Value],"Not found"))} -> 2486 | F27: {=IF($A27="","",_xlfn.XLOOKUP(1,(Table1[Line Item]=$A27)*(Table1[Fiscal Year]=VALUE(RIGHT(F$1,4))),Table1[Value],"Not found"))} -> 651 | G27: {=IF($A27="","",_xlfn.XLOOKUP(1,(Table1[Line Item]=$A27)*(Table1[Fiscal Year]=VALUE(RIGHT(G$1,4))),Table1[Value],"Not found"))} -> 1698 | H27: {=IF($A27="","",_xlfn.XLOOKUP(1,(Table1[Line Item]=$A27)*(Table1[Fiscal Year]=VALUE(RIGHT(H$1,4))),Table1[Value],"Not found"))} -> 232 | I27: {=IF($A27="","",_xlfn.XLOOKUP(1,(Table1[Line Item]=$A27)*(Table1[Fiscal Year]=VALUE(RIGHT(I$1,4))),Table1[Value],"Not found"))} -> 175
A28: income tax expense | B28: {=IF($A28="","",_xlfn.XLOOKUP(1,(Table1[Line Item]=$A28)*(Table1[Fiscal Year]=VALUE(RIGHT(B$1,4))),Table1[Value],"Not found"))} -> -392 | C28: {=IF($A28="","",_xlfn.XLOOKUP(1,(Table1[Line Item]=$A28)*(Table1[Fiscal Year]=VALUE(RIGHT(C$1,4))),Table1[Value],"Not found"))} -> -540 | D28: {=IF($A28="","",_xlfn.XLOOKUP(1,(Table1[Line Item]=$A28)*(Table1[Fiscal Year]=VALUE(RIGHT(D$1,4))),Table1[Value],"Not found"))} -> -597 | E28: {=IF($A28="","",_xlfn.XLOOKUP(1,(Table1[Line Item]=$A28)*(Table1[Fiscal Year]=VALUE(RIGHT(E$1,4))),Table1[Value],"Not found"))} -> -622 | F28: {=IF($A28="","",_xlfn.XLOOKUP(1,(Table1[Line Item]=$A28)*(Table1[Fiscal Year]=VALUE(RIGHT(F$1,4))),Table1[Value],"Not found"))} -> -228 | G28: {=IF($A28="","",_xlfn.XLOOKUP(1,(Table1[Line Item]=$A28)*(Table1[Fiscal Year]=VALUE(RIGHT(G$1,4))),Table1[Value],"Not found"))} -> -475 | H28: {=IF($A28="","",_xlfn.XLOOKUP(1,(Table1[Line Item]=$A28)*(Table1[Fiscal Year]=VALUE(RIGHT(H$1,4))),Table1[Value],"Not found"))} -> -174 | I28: {=IF($A28="","",_xlfn.XLOOKUP(1,(Table1[Line Item]=$A28)*(Table1[Fiscal Year]=VALUE(RIGHT(I$1,4))),Table1[Value],"Not found"))} -> -201
A29: effective tax rate % | B29: {=IF($A29="","",_xlfn.XLOOKUP(1,(Table1[Line Item]=$A29)*(Table1[Fiscal Year]=VALUE(RIGHT(B$1,4))),Table1[Value],"Not found"))} -> 0.29 | C29: {=IF($A29="","",_xlfn.XLOOKUP(1,(Table1[Line Item]=$A29)*(Table1[Fiscal Year]=VALUE(RIGHT(C$1,4))),Table1[Value],"Not found"))} -> 0.28 | D29: {=IF($A29="","",_xlfn.XLOOKUP(1,(Table1[Line Item]=$A29)*(Table1[Fiscal Year]=VALUE(RIGHT(D$1,4))),Table1[Value],"Not found"))} -> 0.26 | E29: {=IF($A29="","",_xlfn.XLOOKUP(1,(Table1[Line Item]=$A29)*(Table1[Fiscal Year]=VALUE(RIGHT(E$1,4))),Table1[Value],"Not found"))} -> 0.25 | F29: {=IF($A29="","",_xlfn.XLOOKUP(1,(Table1[Line Item]=$A29)*(Table1[Fiscal Year]=VALUE(RIGHT(F$1,4))),Table1[Value],"Not found"))} -> 0.35 | G29: {=IF($A29="","",_xlfn.XLOOKUP(1,(Table1[Line Item]=$A29)*(Table1[Fiscal Year]=VALUE(RIGHT(G$1,4))),Table1[Value],"Not found"))} -> 0.28 | H29: {=IF($A29="","",_xlfn.XLOOKUP(1,(Table1[Line Item]=$A29)*(Table1[Fiscal Year]=VALUE(RIGHT(H$1,4))),Table1[Value],"Not found"))} -> 0.75 | I29: {=IF($A29="","",_xlfn.XLOOKUP(1,(Table1[Line Item]=$A29)*(Table1[Fiscal Year]=VALUE(RIGHT(I$1,4))),Table1[Value],"Not found"))} -> 1.149
B30: {=IF($A30="","",_xlfn.XLOOKUP(1,(Table1[Line Item]=$A30)*(Table1[Fiscal Year]=VALUE(RIGHT(B$1,4))),Table1[Value],"Not found"))} | C30: {=IF($A30="","",_xlfn.XLOOKUP(1,(Table1[Line Item]=$A30)*(Table1[Fiscal Year]=VALUE(RIGHT(C$1,4))),Table1[Value],"Not found"))} | D30: {=IF($A30="","",_xlfn.XLOOKUP(1,(Table1[Line Item]=$A30)*(Table1[Fiscal Year]=VALUE(RIGHT(D$1,4))),Table1[Value],"Not found"))} | E30: {=IF($A30="","",_xlfn.XLOOKUP(1,(Table1[Line Item]=$A30)*(Table1[Fiscal Year]=VALUE(RIGHT(E$1,4))),Table1[Value],"Not found"))} | F30: {=IF($A30="","",_xlfn.XLOOKUP(1,(Table1[Line Item]=$A30)*(Table1[Fiscal Year]=VALUE(RIGHT(F$1,4))),Table1[Value],"Not found"))} | G30: {=IF($A30="","",_xlfn.XLOOKUP(1,(Table1[Line Item]=$A30)*(Table1[Fiscal Year]=VALUE(RIGHT(G$1,4))),Table1[Value],"Not found"))} | H30: {=IF($A30="","",_xlfn.XLOOKUP(1,(Table1[Line Item]=$A30)*(Table1[Fiscal Year]=VALUE(RIGHT(H$1,4))),Table1[Value],"Not found"))} | I30: {=IF($A30="","",_xlfn.XLOOKUP(1,(Table1[Line Item]=$A30)*(Table1[Fiscal Year]=VALUE(RIGHT(I$1,4))),Table1[Value],"Not found"))}
A31: net income from continuing ops. | B31: {=IF($A31="","",_xlfn.XLOOKUP(1,(Table1[Line Item]=$A31)*(Table1[Fiscal Year]=VALUE(RIGHT(B$1,4))),Table1[Value],"Not found"))} -> 961 | C31: {=IF($A31="","",_xlfn.XLOOKUP(1,(Table1[Line Item]=$A31)*(Table1[Fiscal Year]=VALUE(RIGHT(C$1,4))),Table1[Value],"Not found"))} -> 1387 | D31: {=IF($A31="","",_xlfn.XLOOKUP(1,(Table1[Line Item]=$A31)*(Table1[Fiscal Year]=VALUE(RIGHT(D$1,4))),Table1[Value],"Not found"))} -> 1701 | E31: {=IF($A31="","",_xlfn.XLOOKUP(1,(Table1[Line Item]=$A31)*(Table1[Fiscal Year]=VALUE(RIGHT(E$1,4))),Table1[Value],"Not found"))} -> 1864 | F31: {=IF($A31="","",_xlfn.XLOOKUP(1,(Table1[Line Item]=$A31)*(Table1[Fiscal Year]=VALUE(RIGHT(F$1,4))),Table1[Value],"Not found"))} -> 423 | G31: {=IF($A31="","",_xlfn.XLOOKUP(1,(Table1[Line Item]=$A31)*(Table1[Fiscal Year]=VALUE(RIGHT(G$1,4))),Table1[Value],"Not found"))} -> 1223 | H31: {=IF($A31="","",_xlfn.XLOOKUP(1,(Table1[Line Item]=$A31)*(Table1[Fiscal Year]=VALUE(RIGHT(H$1,4))),Table1[Value],"Not found"))} -> 58 | I31: {=IF($A31="","",_xlfn.XLOOKUP(1,(Table1[Line Item]=$A31)*(Table1[Fiscal Year]=VALUE(RIGHT(I$1,4))),Table1[Value],"Not found"))} -> -26
A32: net income (total) | B32: {=IF($A32="","",_xlfn.XLOOKUP(1,(Table1[Line Item]=$A32)*(Table1[Fiscal Year]=VALUE(RIGHT(B$1,4))),Table1[Value],"Not found"))} -> 961 | C32: {=IF($A32="","",_xlfn.XLOOKUP(1,(Table1[Line Item]=$A32)*(Table1[Fiscal Year]=VALUE(RIGHT(C$1,4))),Table1[Value],"Not found"))} -> 1387 | D32: {=IF($A32="","",_xlfn.XLOOKUP(1,(Table1[Line Item]=$A32)*(Table1[Fiscal Year]=VALUE(RIGHT(D$1,4))),Table1[Value],"Not found"))} -> 1701 | E32: {=IF($A32="","",_xlfn.XLOOKUP(1,(Table1[Line Item]=$A32)*(Table1[Fiscal Year]=VALUE(RIGHT(E$1,4))),Table1[Value],"Not found"))} -> 1864 | F32: {=IF($A32="","",_xlfn.XLOOKUP(1,(Table1[Line Item]=$A32)*(Table1[Fiscal Year]=VALUE(RIGHT(F$1,4))),Table1[Value],"Not found"))} -> 353 | G32: {=IF($A32="","",_xlfn.XLOOKUP(1,(Table1[Line Item]=$A32)*(Table1[Fiscal Year]=VALUE(RIGHT(G$1,4))),Table1[Value],"Not found"))} -> 1455 | H32: {=IF($A32="","",_xlfn.XLOOKUP(1,(Table1[Line Item]=$A32)*(Table1[Fiscal Year]=VALUE(RIGHT(H$1,4))),Table1[Value],"Not found"))} -> 58 | I32: {=IF($A32="","",_xlfn.XLOOKUP(1,(Table1[Line Item]=$A32)*(Table1[Fiscal Year]=VALUE(RIGHT(I$1,4))),Table1[Value],"Not found"))} -> -26
A33: less: minority interest | B33: {=IF($A33="","",_xlfn.XLOOKUP(1,(Table1[Line Item]=$A33)*(Table1[Fiscal Year]=VALUE(RIGHT(B$1,4))),Table1[Value],"Not found"))} -> -12 | C33: {=IF($A33="","",_xlfn.XLOOKUP(1,(Table1[Line Item]=$A33)*(Table1[Fiscal Year]=VALUE(RIGHT(C$1,4))),Table1[Value],"Not found"))} -> -14 | D33: {=IF($A33="","",_xlfn.XLOOKUP(1,(Table1[Line Item]=$A33)*(Table1[Fiscal Year]=VALUE(RIGHT(D$1,4))),Table1[Value],"Not found"))} -> -11 | E33: {=IF($A33="","",_xlfn.XLOOKUP(1,(Table1[Line Item]=$A33)*(Table1[Fiscal Year]=VALUE(RIGHT(E$1,4))),Table1[Value],"Not found"))} -> -9 | F33: {=IF($A33="","",_xlfn.XLOOKUP(1,(Table1[Line Item]=$A33)*(Table1[Fiscal Year]=VALUE(RIGHT(F$1,4))),Table1[Value],"Not found"))} -> -6 | G33: {=IF($A33="","",_xlfn.XLOOKUP(1,(Table1[Line Item]=$A33)*(Table1[Fiscal Year]=VALUE(RIGHT(G$1,4))),Table1[Value],"Not found"))} -> -8 | H33: {=IF($A33="","",_xlfn.XLOOKUP(1,(Table1[Line Item]=$A33)*(Table1[Fiscal Year]=VALUE(RIGHT(H$1,4))),Table1[Value],"Not found"))} -> -8 | I33: {=IF($A33="","",_xlfn.XLOOKUP(1,(Table1[Line Item]=$A33)*(Table1[Fiscal Year]=VALUE(RIGHT(I$1,4))),Table1[Value],"Not found"))} -> -7
A34: net income attrib. to shareholders | B34: {=IF($A34="","",_xlfn.XLOOKUP(1,(Table1[Line Item]=$A34)*(Table1[Fiscal Year]=VALUE(RIGHT(B$1,4))),Table1[Value],"Not found"))} -> 949 | C34: {=IF($A34="","",_xlfn.XLOOKUP(1,(Table1[Line Item]=$A34)*(Table1[Fiscal Year]=VALUE(RIGHT(C$1,4))),Table1[Value],"Not found"))} -> 1373 | D34: {=IF($A34="","",_xlfn.XLOOKUP(1,(Table1[Line Item]=$A34)*(Table1[Fiscal Year]=VALUE(RIGHT(D$1,4))),Table1[Value],"Not found"))} -> 1690 | E34: {=IF($A34="","",_xlfn.XLOOKUP(1,(Table1[Line Item]=$A34)*(Table1[Fiscal Year]=VALUE(RIGHT(E$1,4))),Table1[Value],"Not found"))} -> 1855 | F34: {=IF($A34="","",_xlfn.XLOOKUP(1,(Table1[Line Item]=$A34)*(Table1[Fiscal Year]=VALUE(RIGHT(F$1,4))),Table1[Value],"Not found"))} -> 347 | G34: {=IF($A34="","",_xlfn.XLOOKUP(1,(Table1[Line Item]=$A34)*(Table1[Fiscal Year]=VALUE(RIGHT(G$1,4))),Table1[Value],"Not found"))} -> 1447 | H34: {=IF($A34="","",_xlfn.XLOOKUP(1,(Table1[Line Item]=$A34)*(Table1[Fiscal Year]=VALUE(RIGHT(H$1,4))),Table1[Value],"Not found"))} -> 50 | I34: {=IF($A34="","",_xlfn.XLOOKUP(1,(Table1[Line Item]=$A34)*(Table1[Fiscal Year]=VALUE(RIGHT(I$1,4))),Table1[Value],"Not found"))} -> -33
B35: {=IF($A35="","",_xlfn.XLOOKUP(1,(Table1[Line Item]=$A35)*(Table1[Fiscal Year]=VALUE(RIGHT(B$1,4))),Table1[Value],"Not found"))} | C35: {=IF($A35="","",_xlfn.XLOOKUP(1,(Table1[Line Item]=$A35)*(Table1[Fiscal Year]=VALUE(RIGHT(C$1,4))),Table1[Value],"Not found"))} | D35: {=IF($A35="","",_xlfn.XLOOKUP(1,(Table1[Line Item]=$A35)*(Table1[Fiscal Year]=VALUE(RIGHT(D$1,4))),Table1[Value],"Not found"))} | E35: {=IF($A35="","",_xlfn.XLOOKUP(1,(Table1[Line Item]=$A35)*(Table1[Fiscal Year]=VALUE(RIGHT(E$1,4))),Table1[Value],"Not found"))} | F35: {=IF($A35="","",_xlfn.XLOOKUP(1,(Table1[Line Item]=$A35)*(Table1[Fiscal Year]=VALUE(RIGHT(F$1,4))),Table1[Value],"Not found"))} | G35: {=IF($A35="","",_xlfn.XLOOKUP(1,(Table1[Line Item]=$A35)*(Table1[Fiscal Year]=VALUE(RIGHT(G$1,4))),Table1[Value],"Not found"))} | H35: {=IF($A35="","",_xlfn.XLOOKUP(1,(Table1[Line Item]=$A35)*(Table1[Fiscal Year]=VALUE(RIGHT(H$1,4))),Table1[Value],"Not found"))} | I35: {=IF($A35="","",_xlfn.XLOOKUP(1,(Table1[Line Item]=$A35)*(Table1[Fiscal Year]=VALUE(RIGHT(I$1,4))),Table1[Value],"Not found"))}
A36: basic eps | B36: {=IF($A36="","",_xlfn.XLOOKUP(1,(Table1[Line Item]=$A36)*(Table1[Fiscal Year]=VALUE(RIGHT(B$1,4))),Table1[Value],"Not found"))} -> 4.72 | C36: {=IF($A36="","",_xlfn.XLOOKUP(1,(Table1[Line Item]=$A36)*(Table1[Fiscal Year]=VALUE(RIGHT(C$1,4))),Table1[Value],"Not found"))} -> 6.78 | D36: {=IF($A36="","",_xlfn.XLOOKUP(1,(Table1[Line Item]=$A36)*(Table1[Fiscal Year]=VALUE(RIGHT(D$1,4))),Table1[Value],"Not found"))} -> 8.45 | E36: {=IF($A36="","",_xlfn.XLOOKUP(1,(Table1[Line Item]=$A36)*(Table1[Fiscal Year]=VALUE(RIGHT(E$1,4))),Table1[Value],"Not found"))} -> 9.48 | F36: {=IF($A36="","",_xlfn.XLOOKUP(1,(Table1[Line Item]=$A36)*(Table1[Fiscal Year]=VALUE(RIGHT(F$1,4))),Table1[Value],"Not found"))} -> 1.79 | G36: {=IF($A36="","",_xlfn.XLOOKUP(1,(Table1[Line Item]=$A36)*(Table1[Fiscal Year]=VALUE(RIGHT(G$1,4))),Table1[Value],"Not found"))} -> 7.39 | H36: {=IF($A36="","",_xlfn.XLOOKUP(1,(Table1[Line Item]=$A36)*(Table1[Fiscal Year]=VALUE(RIGHT(H$1,4))),Table1[Value],"Not found"))} -> 0.27 | I36: {=IF($A36="","",_xlfn.XLOOKUP(1,(Table1[Line Item]=$A36)*(Table1[Fiscal Year]=VALUE(RIGHT(I$1,4))),Table1[Value],"Not found"))} -> -0.18
A37: diluted eps | B37: {=IF($A37="","",_xlfn.XLOOKUP(1,(Table1[Line Item]=$A37)*(Table1[Fiscal Year]=VALUE(RIGHT(B$1,4))),Table1[Value],"Not found"))} -> 4.7 | C37: {=IF($A37="","",_xlfn.XLOOKUP(1,(Table1[Line Item]=$A37)*(Table1[Fiscal Year]=VALUE(RIGHT(C$1,4))),Table1[Value],"Not found"))} -> 6.75 | D37: {=IF($A37="","",_xlfn.XLOOKUP(1,(Table1[Line Item]=$A37)*(Table1[Fiscal Year]=VALUE(RIGHT(D$1,4))),Table1[Value],"Not found"))} -> 8.42 | E37: {=IF($A37="","",_xlfn.XLOOKUP(1,(Table1[Line Item]=$A37)*(Table1[Fiscal Year]=VALUE(RIGHT(E$1,4))),Table1[Value],"Not found"))} -> 9.44 | F37: {=IF($A37="","",_xlfn.XLOOKUP(1,(Table1[Line Item]=$A37)*(Table1[Fiscal Year]=VALUE(RIGHT(F$1,4))),Table1[Value],"Not found"))} -> 1.78 | G37: {=IF($A37="","",_xlfn.XLOOKUP(1,(Table1[Line Item]=$A37)*(Table1[Fiscal Year]=VALUE(RIGHT(G$1,4))),Table1[Value],"Not found"))} -> 7.36 | H37: {=IF($A37="","",_xlfn.XLOOKUP(1,(Table1[Line Item]=$A37)*(Table1[Fiscal Year]=VALUE(RIGHT(H$1,4))),Table1[Value],"Not found"))} -> 0.27 | I37: {=IF($A37="","",_xlfn.XLOOKUP(1,(Table1[Line Item]=$A37)*(Table1[Fiscal Year]=VALUE(RIGHT(I$1,4))),Table1[Value],"Not found"))} -> -0.18
A38: wtd. avg shares - basic (mn) | B38: {=IF($A38="","",_xlfn.XLOOKUP(1,(Table1[Line Item]=$A38)*(Table1[Fiscal Year]=VALUE(RIGHT(B$1,4))),Table1[Value],"Not found"))} -> 201 | C38: {=IF($A38="","",_xlfn.XLOOKUP(1,(Table1[Line Item]=$A38)*(Table1[Fiscal Year]=VALUE(RIGHT(C$1,4))),Table1[Value],"Not found"))} -> 202.5 | D38: {=IF($A38="","",_xlfn.XLOOKUP(1,(Table1[Line Item]=$A38)*(Table1[Fiscal Year]=VALUE(RIGHT(D$1,4))),Table1[Value],"Not found"))} -> 200 | E38: {=IF($A38="","",_xlfn.XLOOKUP(1,(Table1[Line Item]=$A38)*(Table1[Fiscal Year]=VALUE(RIGHT(E$1,4))),Table1[Value],"Not found"))} -> 195.7 | F38: {=IF($A38="","",_xlfn.XLOOKUP(1,(Table1[Line Item]=$A38)*(Table1[Fiscal Year]=VALUE(RIGHT(F$1,4))),Table1[Value],"Not found"))} -> 194.3 | G38: {=IF($A38="","",_xlfn.XLOOKUP(1,(Table1[Line Item]=$A38)*(Table1[Fiscal Year]=VALUE(RIGHT(G$1,4))),Table1[Value],"Not found"))} -> 195.8 | H38: {=IF($A38="","",_xlfn.XLOOKUP(1,(Table1[Line Item]=$A38)*(Table1[Fiscal Year]=VALUE(RIGHT(H$1,4))),Table1[Value],"Not found"))} -> 183.5 | I38: {=IF($A38="","",_xlfn.XLOOKUP(1,(Table1[Line Item]=$A38)*(Table1[Fiscal Year]=VALUE(RIGHT(I$1,4))),Table1[Value],"Not found"))} -> 178.6
A39: wtd. avg shares - diluted (mn) | B39: {=IF($A39="","",_xlfn.XLOOKUP(1,(Table1[Line Item]=$A39)*(Table1[Fiscal Year]=VALUE(RIGHT(B$1,4))),Table1[Value],"Not found"))} -> 201.8 | C39: {=IF($A39="","",_xlfn.XLOOKUP(1,(Table1[Line Item]=$A39)*(Table1[Fiscal Year]=VALUE(RIGHT(C$1,4))),Table1[Value],"Not found"))} -> 203.3 | D39: {=IF($A39="","",_xlfn.XLOOKUP(1,(Table1[Line Item]=$A39)*(Table1[Fiscal Year]=VALUE(RIGHT(D$1,4))),Table1[Value],"Not found"))} -> 200.8 | E39: {=IF($A39="","",_xlfn.XLOOKUP(1,(Table1[Line Item]=$A39)*(Table1[Fiscal Year]=VALUE(RIGHT(E$1,4))),Table1[Value],"Not found"))} -> 196.5 | F39: {=IF($A39="","",_xlfn.XLOOKUP(1,(Table1[Line Item]=$A39)*(Table1[Fiscal Year]=VALUE(RIGHT(F$1,4))),Table1[Value],"Not found"))} -> 195.1 | G39: {=IF($A39="","",_xlfn.XLOOKUP(1,(Table1[Line Item]=$A39)*(Table1[Fiscal Year]=VALUE(RIGHT(G$1,4))),Table1[Value],"Not found"))} -> 196.6 | H39: {=IF($A39="","",_xlfn.XLOOKUP(1,(Table1[Line Item]=$A39)*(Table1[Fiscal Year]=VALUE(RIGHT(H$1,4))),Table1[Value],"Not found"))} -> 184.2 | I39: {=IF($A39="","",_xlfn.XLOOKUP(1,(Table1[Line Item]=$A39)*(Table1[Fiscal Year]=VALUE(RIGHT(I$1,4))),Table1[Value],"Not found"))} -> 179.3
A40: dividend per share (dps) | B40: {=IF($A40="","",_xlfn.XLOOKUP(1,(Table1[Line Item]=$A40)*(Table1[Fiscal Year]=VALUE(RIGHT(B$1,4))),Table1[Value],"Not found"))} -> 2 | C40: {=IF($A40="","",_xlfn.XLOOKUP(1,(Table1[Line Item]=$A40)*(Table1[Fiscal Year]=VALUE(RIGHT(C$1,4))),Table1[Value],"Not found"))} -> 2.6 | D40: {=IF($A40="","",_xlfn.XLOOKUP(1,(Table1[Line Item]=$A40)*(Table1[Fiscal Year]=VALUE(RIGHT(D$1,4))),Table1[Value],"Not found"))} -> 3.35 | E40: {=IF($A40="","",_xlfn.XLOOKUP(1,(Table1[Line Item]=$A40)*(Table1[Fiscal Year]=VALUE(RIGHT(E$1,4))),Table1[Value],"Not found"))} -> 3.85 | F40: {=IF($A40="","",_xlfn.XLOOKUP(1,(Table1[Line Item]=$A40)*(Table1[Fiscal Year]=VALUE(RIGHT(F$1,4))),Table1[Value],"Not found"))} -> 0 | G40: {=IF($A40="","",_xlfn.XLOOKUP(1,(Table1[Line Item]=$A40)*(Table1[Fiscal Year]=VALUE(RIGHT(G$1,4))),Table1[Value],"Not found"))} -> 3.3 | H40: {=IF($A40="","",_xlfn.XLOOKUP(1,(Table1[Line Item]=$A40)*(Table1[Fiscal Year]=VALUE(RIGHT(H$1,4))),Table1[Value],"Not found"))} -> 0.7 | I40: {=IF($A40="","",_xlfn.XLOOKUP(1,(Table1[Line Item]=$A40)*(Table1[Fiscal Year]=VALUE(RIGHT(I$1,4))),Table1[Value],"Not found"))} -> 0.7

Sheet Trend Analysis(Stage4-Q1)
A1: Fiscal Year | B1: FY2016 | C1: FY2017 | D1: FY2018 | E1: FY2019 | F1: FY2020 | G1: FY2021 | H1: FY2022 | I1: FY2023
A2: Revenue YoY | B2: N/A | C2: =('MASTER P&L'!C$6-'MASTER P&L'!B$6)/'MASTER P&L'!B$6 -> 0.14797381 | D2: =('MASTER P&L'!D$6-'MASTER P&L'!C$6)/'MASTER P&L'!C$6 -> 0.032849467 | E2: =('MASTER P&L'!E$6-'MASTER P&L'!D$6)/'MASTER P&L'!D$6 -> 0.07871321 | F2: =('MASTER P&L'!F$6-'MASTER P&L'!E$6)/'MASTER P&L'!E$6 -> -0.1605753 | G2: =('MASTER P&L'!G$6-'MASTER P&L'!F$6)/'MASTER P&L'!F$6 -> 0.070046362 | H2: =('MASTER P&L'!H$6-'MASTER P&L'!G$6)/'MASTER P&L'!G$6 -> 0.060139399 | I2: =('MASTER P&L'!I$6-'MASTER P&L'!H$6)/'MASTER P&L'!H$6 -> -0.048154236
A3: Gross Profit YoY | B3: N/A | C3: =('MASTER P&L'!C$10-'MASTER P&L'!B$10)/'MASTER P&L'!B$10 -> 0.19047089 | D3: =('MASTER P&L'!D$10-'MASTER P&L'!C$10)/'MASTER P&L'!C$10 -> 0.057415373 | E3: =('MASTER P&L'!E$10-'MASTER P&L'!D$10)/'MASTER P&L'!D$10 -> 0.087106473 | F3: =('MASTER P&L'!F$10-'MASTER P&L'!E$10)/'MASTER P&L'!E$10 -> -0.19775482 | G3: =('MASTER P&L'!G$10-'MASTER P&L'!F$10)/'MASTER P&L'!F$10 -> 0.087304806 | H3: =('MASTER P&L'!H$10-'MASTER P&L'!G$10)/'MASTER P&L'!G$10 -> -0.0069943113 | I3: =('MASTER P&L'!I$10-'MASTER P&L'!H$10)/'MASTER P&L'!H$10 -> -0.044139745
A4: EBIT YoY | B4: N/A | C4: =('MASTER P&L'!C$22-'MASTER P&L'!B$22)/'MASTER P&L'!B$22 -> 0.41080313 | D4: =('MASTER P&L'!D$22-'MASTER P&L'!C$22)/'MASTER P&L'!C$22 -> 0.18942065 | E4: =('MASTER P&L'!E$22-'MASTER P&L'!D$22)/'MASTER P&L'!D$22 -> 0.10969928 | F4: =('MASTER P&L'!F$22-'MASTER P&L'!E$22)/'MASTER P&L'!E$22 -> -0.69351145 | G4: =('MASTER P&L'!G$22-'MASTER P&L'!F$22)/'MASTER P&L'!F$22 -> 1.2914072 | H4: =('MASTER P&L'!H$22-'MASTER P&L'!G$22)/'MASTER P&L'!G$22 -> -0.78967391 | I4: =('MASTER P&L'!I$22-'MASTER P&L'!H$22)/'MASTER P&L'!H$22 -> -0.082687339
A5: Net Income YoY | B5: N/A | C5: =('MASTER P&L'!C$32-'MASTER P&L'!B$32)/'MASTER P&L'!B$32 -> 0.44328824 | D5: =('MASTER P&L'!D$32-'MASTER P&L'!C$32)/'MASTER P&L'!C$32 -> 0.22638789 | E5: =('MASTER P&L'!E$32-'MASTER P&L'!D$32)/'MASTER P&L'!D$32 -> 0.095825985 | F5: =('MASTER P&L'!F$32-'MASTER P&L'!E$32)/'MASTER P&L'!E$32 -> -0.81062232 | G5: =('MASTER P&L'!G$32-'MASTER P&L'!F$32)/'MASTER P&L'!F$32 -> 3.121813 | H5: =('MASTER P&L'!H$32-'MASTER P&L'!G$32)/'MASTER P&L'!G$32 -> -0.96013746 | I5: =('MASTER P&L'!I$32-'MASTER P&L'!H$32)/'MASTER P&L'!H$32 -> -1.4482759
A13: FY2017 Revenue YoY=
A14: (FY2017 Revenue - FY2016 Revenue) / FY2016 Revenue
A16: FY2017 Gross Profit YoY=
A17: (FY2017 Gross Profit - FY2016 Gross Profit) / FY2016 Gross Profit
A19: FY2017 EBIT YoY=
A20: (FY2017 EBIT - FY2016 EBIT) / FY2016 EBIT
A22: FY2017 Net Income YoY=
A23: (FY2017 Net Income - FY2016 Net Income) / FY2016 Net Income

Sheet CAGR(Stage4-Q2)
A1: CAGR=((ending value/Beginning value )^1/n ) -1 | J1: Revenue CAGR
J2: (FY2023 Revenue/FY2016 Revenue)^(1/7)-1 | O2: Metric | P2: FY2016 | Q2: FY2023 | R2: CAGR
O3: Revenue | P3: ='MASTER P&L'!B6 -> 18483 | Q3: ='MASTER P&L'!I6 -> 21427 | R3: 0.0213
A4: You have FY2016 → FY2023, which is 7 years | J4: =(Q3/P3) -> 1.1592815 | O4: Net Income (Total) | P4: 961 | Q4: -26 | R4: N/M
J5: =(J4)^(1/7) -> 1.0213388
A6: FY2016 → FY2017 = 1 | J6: =J5-1 -> 0.02133883
A7: FY2017 → FY2018 = 2 | J7: 0.0213
A8: FY2018 → FY2019 = 3
A9: FY2019 → FY2020 = 4
A10: FY2020 → FY2021 = 5
A11: FY2021 → FY2022 = 6
A12: FY2022 → FY2023 = 7 | J12: Net Income CAGR
J14: (FY2023 Net Income/FY2016 Net Income)^(1/7)-1
J16: =(Q4/P4) -> -0.027055151
J17: =(J16)^(1/7) -> -0.59708438
J18: =J17-1 -> -1.5970844

Sheet Index Tables(Stage4-Q3)
A1: Fiscal Year | B1: FY2016 | C1: FY2017 | D1: FY2018 | E1: FY2019 | F1: FY2020 | G1: FY2021 | H1: FY2022 | I1: FY2023
A2: Revenue Index | B2: 100 | C2: =('MASTER P&L'!C$6/'MASTER P&L'!$B$6)*100 -> 114.79738 | D2: =('MASTER P&L'!D$6/'MASTER P&L'!$B$6)*100 -> 118.56841 | E2: =('MASTER P&L'!E$6/'MASTER P&L'!$B$6)*100 -> 127.90131 | F2: =('MASTER P&L'!F$6/'MASTER P&L'!$B$6)*100 -> 107.36352 | G2: =('MASTER P&L'!G$6/'MASTER P&L'!$B$6)*100 -> 114.88395 | H2: =('MASTER P&L'!H$6/'MASTER P&L'!$B$6)*100 -> 121.793 | I2: =('MASTER P&L'!I$6/'MASTER P&L'!$B$6)*100 -> 115.92815
A3: Gross Profit Index | B3: 100 | C3: =('MASTER P&L'!C$10/'MASTER P&L'!$B$10)*100 -> 119.04709 | D3: =('MASTER P&L'!D$10/'MASTER P&L'!$B$10)*100 -> 125.88222 | E3: =('MASTER P&L'!E$10/'MASTER P&L'!$B$10)*100 -> 136.84738 | F3: =('MASTER P&L'!F$10/'MASTER P&L'!$B$10)*100 -> 109.78515 | G3: =('MASTER P&L'!G$10/'MASTER P&L'!$B$10)*100 -> 119.36992 | H3: =('MASTER P&L'!H$10/'MASTER P&L'!$B$10)*100 -> 118.53501 | I3: =('MASTER P&L'!I$10/'MASTER P&L'!$B$10)*100 -> 113.30291 | J3: Formula=Current year's value ÷ FY2016 value × 100
A4: Operating Expenses Index | B4: 100 | C4: =('MASTER P&L'!C$19/'MASTER P&L'!$B$19)*100 -> 114.79855 | D4: =('MASTER P&L'!D$19/'MASTER P&L'!$B$19)*100 -> 118.01395 | E4: =('MASTER P&L'!E$19/'MASTER P&L'!$B$19)*100 -> 127.59556 | F4: =('MASTER P&L'!F$19/'MASTER P&L'!$B$19)*100 -> 118.89205 | G4: =('MASTER P&L'!G$19/'MASTER P&L'!$B$19)*100 -> 116.8001 | H4: =('MASTER P&L'!H$19/'MASTER P&L'!$B$19)*100 -> 132.25723 | I4: =('MASTER P&L'!I$19/'MASTER P&L'!$B$19)*100 -> 128.93853
J5: The whole purpose of an index is to measure every year against the same base year, FY2016
H11: The indexed series shows that revenue increased to 115.93 by FY2023, while gross profit reached 113.30. In contrast, operating expenses rose to 128.94, growing substantially faster than both revenue and gross profit. This divergence indicates increasing operating-cost pressure and suggests weaker operating leverage over the period. The sharp movements around FY2020 and FY2021 also show that the business experienced a significant disruption followed by a recovery.

Sheet Stage4-Q4
A1: Metric | B1: Best Year | C1: Best Value | D1: Worst Year | E1: Worst Value
A2: Revenue | B2: =_xlfn.XLOOKUP(C2,'MASTER P&L'!B6:I6,'MASTER P&L'!B1:I1) -> FY2019 | C2: =MAX('MASTER P&L'!B6:I6) -> 23640 | D2: =_xlfn.XLOOKUP(E2,'MASTER P&L'!B6:I6,'MASTER P&L'!B1:I1) -> FY2016 | E2: =MIN('MASTER P&L'!B6:I6) -> 18483
A3: Operating Profit (EBIT) | B3: =_xlfn.XLOOKUP(C3,'MASTER P&L'!B22:I22,'MASTER P&L'!B1:I1) -> FY2019 | C3: =MAX('MASTER P&L'!B22:I22) -> 2620 | D3: =_xlfn.XLOOKUP(E3,'MASTER P&L'!B22:I22,'MASTER P&L'!B1:I1) -> FY2023 | E3: =MIN('MASTER P&L'!B22:I22) -> 355 | H3: Basic EPS=Net income attributable to ordinary shareholders/Weighted average basic shares
A4: Basic EPS | B4: =_xlfn.XLOOKUP(C4,'MASTER P&L'!B36:I36,'MASTER P&L'!$B1:$I1) -> FY2019 | C4: =MAX('MASTER P&L'!B36:I36) -> 9.48 | D4: =_xlfn.XLOOKUP(E4,'MASTER P&L'!B36:I36,'MASTER P&L'!$B1:$I1) -> FY2023 | E4: =MIN('MASTER P&L'!B36:I36) -> -0.18

Sheet Stage4-Q5
A1: Revenue growth=(Revenue2023/Revenue2016)−1
G3: =('MASTER P&L'!I6/'MASTER P&L'!B6)-1 -> 0.1592815 | J3: This indicates weakening operating leverage over the period, as the business incurred substantially higher operating costs relative to its revenue growth. In other words, the company did not achieve sufficient revenue growth to absorb the increase in operating expenses, putting pressure on operating profitability.
A8: Operating expense growth=(OpEx2023/OpEx2016)−1
G10: =('MASTER P&L'!I19/'MASTER P&L'!B19)-1 -> 0.28938533

Sheet Stage 5 -Q1
A1: ratios | B1: FY2016 | C1: FY2017 | D1: FY2018 | E1: FY2019 | F1: FY2020 | G1: FY2021 | H1: FY2022 | I1: FY2023
A2: Gross Margin % = Gross Profit ÷ Total Net Revenue | B2: =('MASTER P&L'!B$10/'MASTER P&L'!B$6)*100 -> 48.601418 | C2: =('MASTER P&L'!C$10/'MASTER P&L'!C$6)*100 -> 50.400603 | D2: =('MASTER P&L'!D$10/'MASTER P&L'!D$6)*100 -> 51.599361 | E2: =('MASTER P&L'!E$10/'MASTER P&L'!E$6)*100 -> 52.000846 | F2: =('MASTER P&L'!F$10/'MASTER P&L'!F$6)*100 -> 49.697642 | G2: =('MASTER P&L'!G$10/'MASTER P&L'!G$6)*100 -> 50.499199 | H2: =('MASTER P&L'!H$10/'MASTER P&L'!H$6)*100 -> 47.301319 | I2: =('MASTER P&L'!I$10/'MASTER P&L'!I$6)*100 -> 47.500817
A3: Operating Margin % = EBIT ÷ Total Net Revenue | B3: =('MASTER P&L'!B$22/'MASTER P&L'!B$6)*100 -> 7.6124006 | C3: =('MASTER P&L'!C$22/'MASTER P&L'!C$6)*100 -> 9.3552644 | D3: =('MASTER P&L'!D$22/'MASTER P&L'!D$6)*100 -> 10.773443 | E3: =('MASTER P&L'!E$22/'MASTER P&L'!E$6)*100 -> 11.08291 | F3: =('MASTER P&L'!F$22/'MASTER P&L'!F$6)*100 -> 4.0465632 | G3: =('MASTER P&L'!G$22/'MASTER P&L'!G$6)*100 -> 8.665348 | H3: =('MASTER P&L'!H$22/'MASTER P&L'!H$6)*100 -> 1.7191595 | I3: =('MASTER P&L'!I$22/'MASTER P&L'!I$6)*100 -> 1.6567882
A4: Net Margin % = Net Income Attrib. to Shareholders ÷ Total Net Revenue | B4: =('MASTER P&L'!B$34/'MASTER P&L'!B$6)*100 -> 5.1344479 | C4: =('MASTER P&L'!C$34/'MASTER P&L'!C$6)*100 -> 6.4709209 | D4: =('MASTER P&L'!D$34/'MASTER P&L'!D$6)*100 -> 7.7116131 | E4: =('MASTER P&L'!E$34/'MASTER P&L'!E$6)*100 -> 7.8468697 | F4: =('MASTER P&L'!F$34/'MASTER P&L'!F$6)*100 -> 1.7486394 | G4: =('MASTER P&L'!G$34/'MASTER P&L'!G$6)*100 -> 6.8145427 | H4: =('MASTER P&L'!H$34/'MASTER P&L'!H$6)*100 -> 0.22211363 | I4: =('MASTER P&L'!I$34/'MASTER P&L'!I$6)*100 -> -0.15401129

Sheet Stage5-Q2
A1: FY2019 → starting point FY2023 → ending point | D1: 1. Gross Margin change | I1: 3. Calculate the change
E2: FY2023 Gross Margin % - FY2019 Gross Margin %
F3: ='Stage 5 -Q1'!$I$2-'Stage 5 -Q1'!$E$2 -> -4.5000293 | J3: Line | K3: FY2019 calculation | L3: FY2023 calculation | M3: Change (pp)
J4: Marketing & Point-of-Sale | K4: =(ABS('MASTER P&L'!E15)/'MASTER P&L'!E6)*100 -> 12.800338 | L4: =(ABS('MASTER P&L'!I15)/'MASTER P&L'!I6)*100 -> 12.302235 | M4: =L4-K4 -> -0.49810291
J5: Distribution & Selling | K5: =(ABS('MASTER P&L'!E16)/'MASTER P&L'!E6)*100 -> 22.301184 | L5: =(ABS('MASTER P&L'!I16)/'MASTER P&L'!I6)*100 -> 25.799225 | M5: =L5-K5 -> 3.4980408
J6: General & Administration | K6: =(ABS('MASTER P&L'!E17)/'MASTER P&L'!E6)*100 -> 5.6979695 | L6: =(ABS('MASTER P&L'!I17)/'MASTER P&L'!I6)*100 -> 7.2992019 | M6: =L6-K6 -> 1.6012324
J7: Sundry Expenses | K7: =(ABS('MASTER P&L'!E18)/'MASTER P&L'!E6)*100 -> 0.99830795 | L7: =(ABS('MASTER P&L'!I18)/'MASTER P&L'!I6)*100 -> 1.1994213 | M7: =L7-K7 -> 0.20111334
A8: 2. Each operating expense as % of revenue
C11: Expense / Total Net Revenue * 100 | I11: 4. Find the biggest damage
C12: Marketing FY2019 / Revenue FY2019 * 100
C13: Marketing FY2023 / Revenue FY2023 * 100
J14: Distribution & Selling Expense had the biggest negative impact, increasing by 3.50 percentage points of revenue from FY2019 to FY2023.
B16: Line | C16: FY2019 calculation | D16: FY2023 calculation
B17: Marketing & Point-of-Sale | C17: =(ABS('MASTER P&L'!E15)/'MASTER P&L'!E6)*100 -> 12.800338 | D17: =(ABS('MASTER P&L'!I15)/'MASTER P&L'!I6)*100 -> 12.302235
B18: Distribution & Selling | C18: =(ABS('MASTER P&L'!E16)/'MASTER P&L'!E6)*100 -> 22.301184 | D18: =(ABS('MASTER P&L'!I16)/'MASTER P&L'!I6)*100 -> 25.799225
B19: General & Administration | C19: =(ABS('MASTER P&L'!E17)/'MASTER P&L'!E6)*100 -> 5.6979695 | D19: =(ABS('MASTER P&L'!I17)/'MASTER P&L'!I6)*100 -> 7.2992019
B20: Sundry Expenses | C20: =(ABS('MASTER P&L'!E18)/'MASTER P&L'!E6)*100 -> 0.99830795 | D20: =(ABS('MASTER P&L'!I18)/'MASTER P&L'!I6)*100 -> 1.1994213

Sheet Stage5-Q3
A1: % OF NET SALES | B1: FY2016 calculation | C1: FY2017 calculation | D1: FY2018 calculation | E1: FY2019 calculation | F1: FY2020 calculation | G1: FY2021 calculation | H1: FY2022 calculation | I1: FY2023 calculation
A2: Marketing & Point-of-Sale | B2: =(ABS('MASTER P&L'!B$15)/'MASTER P&L'!B$6) -> 0.13699075 | C2: =(ABS('MASTER P&L'!C$15)/'MASTER P&L'!C$6) -> 0.13399001 | D2: =(ABS('MASTER P&L'!D$15)/'MASTER P&L'!D$6) -> 0.13100616 | E2: =(ABS('MASTER P&L'!E$15)/'MASTER P&L'!E$6) -> 0.12800338 | F2: =(ABS('MASTER P&L'!F$15)/'MASTER P&L'!F$6) -> 0.11897803 | G2: =(ABS('MASTER P&L'!G$15)/'MASTER P&L'!G$6) -> 0.12098521 | H2: =(ABS('MASTER P&L'!H$15)/'MASTER P&L'!H$6) -> 0.12398383 | I2: =(ABS('MASTER P&L'!I$15)/'MASTER P&L'!I$6) -> 0.12302235
A3: Distribution & Selling | B3: =(ABS('MASTER P&L'!B$16)/'MASTER P&L'!B$6) -> 0.21798409 | C3: =(ABS('MASTER P&L'!C$16)/'MASTER P&L'!C$6) -> 0.22198134 | D3: =(ABS('MASTER P&L'!D$16)/'MASTER P&L'!D$6) -> 0.22400183 | E3: =(ABS('MASTER P&L'!E$16)/'MASTER P&L'!E$6) -> 0.22301184 | F3: =(ABS('MASTER P&L'!F$16)/'MASTER P&L'!F$6) -> 0.27000605 | G3: =(ABS('MASTER P&L'!G$16)/'MASTER P&L'!G$6) -> 0.23401149 | H3: =(ABS('MASTER P&L'!H$16)/'MASTER P&L'!H$6) -> 0.24299231 | I3: =(ABS('MASTER P&L'!I$16)/'MASTER P&L'!I$6) -> 0.25799225
A4: General & Administration | B4: =(ABS('MASTER P&L'!B$17)/'MASTER P&L'!B$6) -> 0.053995563 | C4: =(ABS('MASTER P&L'!C$17)/'MASTER P&L'!C$6) -> 0.05302102 | D4: =(ABS('MASTER P&L'!D$17)/'MASTER P&L'!D$6) -> 0.052019165 | E4: =(ABS('MASTER P&L'!E$17)/'MASTER P&L'!E$6) -> 0.056979695 | F4: =(ABS('MASTER P&L'!F$17)/'MASTER P&L'!F$6) -> 0.065007055 | G4: =(ABS('MASTER P&L'!G$17)/'MASTER P&L'!G$6) -> 0.060987096 | H4: =(ABS('MASTER P&L'!H$17)/'MASTER P&L'!H$6) -> 0.078006308 | I4: =(ABS('MASTER P&L'!I$17)/'MASTER P&L'!I$6) -> 0.072992019
A5: Sundry Expenses | B5: =(ABS('MASTER P&L'!B$18)/'MASTER P&L'!B$6) -> 0.010009198 | C5: =(ABS('MASTER P&L'!C$18)/'MASTER P&L'!C$6) -> 0.0099915166 | D5: =(ABS('MASTER P&L'!D$18)/'MASTER P&L'!D$6) -> 0.0099931554 | E5: =(ABS('MASTER P&L'!E$18)/'MASTER P&L'!E$6) -> 0.0099830795 | F5: =(ABS('MASTER P&L'!F$18)/'MASTER P&L'!F$6) -> 0.0099778271 | G5: =(ABS('MASTER P&L'!G$18)/'MASTER P&L'!G$6) -> 0.0099839879 | H5: =(ABS('MASTER P&L'!H$18)/'MASTER P&L'!H$6) -> 0.0099951135 | I5: =(ABS('MASTER P&L'!I$18)/'MASTER P&L'!I$6) -> 0.011994213
A8: Most volatile: Distribution & Selling Expense — ranges from 21.80% to 27.00%, the largest fluctuation.
A9: Most fixed-like: Sundry Expenses — stays around 1.00% throughout.
A10: Downturn implication: A relatively fixed cost base means expenses do not fall as quickly as revenue, putting pressure on operating margins when sales decline.

Sheet Stage5-Q4,Q5
A1: compare FY2022 and FY2023. | B1: FY2022 | C1: FY2023 | H1: FY2016 | I1: FY2017 | J1: FY2018 | K1: FY2019 | L1: FY2020 | M1: FY2021 | N1: FY2022 | O1: FY2023
A2: 1. Financial income | B2: ='MASTER P&L'!H25 -> 44 | C2: ='MASTER P&L'!I25 -> 62 | G2: EPS Reconciliation | H2: ='MASTER P&L'!B$34/'MASTER P&L'!B$38 -> 4.721393 | I2: ='MASTER P&L'!C$34/'MASTER P&L'!C$38 -> 6.7802469 | J2: ='MASTER P&L'!D$34/'MASTER P&L'!D$38 -> 8.45 | K2: ='MASTER P&L'!E$34/'MASTER P&L'!E$38 -> 9.4787941 | L2: ='MASTER P&L'!F$34/'MASTER P&L'!F$38 -> 1.7858981 | M2: ='MASTER P&L'!G$34/'MASTER P&L'!G$38 -> 7.3901941 | N2: ='MASTER P&L'!H$34/'MASTER P&L'!H$38 -> 0.27247956 | O2: ='MASTER P&L'!I$34/'MASTER P&L'!I$38 -> -0.18477044
A3: 2. Financial expenses | B3: ='MASTER P&L'!H26 -> -199 | C3: ='MASTER P&L'!I26 -> -242 | G3: Basic EPS | H3: ='MASTER P&L'!B$36 -> 4.72 | I3: ='MASTER P&L'!C$36 -> 6.78 | J3: ='MASTER P&L'!D$36 -> 8.45 | K3: ='MASTER P&L'!E$36 -> 9.48 | L3: ='MASTER P&L'!F$36 -> 1.79 | M3: ='MASTER P&L'!G$36 -> 7.39 | N3: ='MASTER P&L'!H$36 -> 0.27 | O3: ='MASTER P&L'!I$36 -> -0.18
A4: 3. Income before taxes | B4: ='MASTER P&L'!H27 -> 232 | C4: ='MASTER P&L'!I27 -> 175 | G4: EPS = Net Income Attributable to Shareholders ÷ Weighted Average Shares — Basic
A5: 4. Income tax expense | B5: ='MASTER P&L'!H28 -> -174 | C5: ='MASTER P&L'!I28 -> -201
A6: 5. Net income attributable to shareholders | B6: ='MASTER P&L'!H34 -> 50 | C6: ='MASTER P&L'!I34 -> -33 | G6: Calculate profit change | J6: (FY2023 Net Income − FY2019 Net Income) ÷ FY2019 Net Income × 100
A7: 6.Operating Margin | B7: ='MASTER P&L'!H23 -> 0.017 | C7: ='MASTER P&L'!I23 -> 0.017 | J7: =(('MASTER P&L'!I32-'MASTER P&L'!E32)/'MASTER P&L'!E32)*100 -> -101.39485
A8: 7.Net Margin | B8: =('MASTER P&L'!H34/'MASTER P&L'!H6)*100 -> 0.22211363 | C8: =('MASTER P&L'!I34/'MASTER P&L'!I6)*100 -> -0.15401129
G9: Calculate share-count change | K9: (FY2023 Shares − FY2019 Shares) ÷ FY2019 Shares × 100
K11: =(('MASTER P&L'!I38-'MASTER P&L'!E38)/'MASTER P&L'!E38)*100 -> -8.7378641
G13: Interpretation: Net income fell by 101.39%, which was the main driver of the sharp decline in EPS. Basic weighted average shares fell by 8.74%, which partially offset the EPS decline because fewer shares were outstanding. Therefore, the EPS movement was driven overwhelmingly by the deterioration in profit, not by the change in share count.

Sheet Stage5-Q6
A1: Question: In one year, the effective tax rate exceeds 100%.
A3: Answer: | B3: FY2023 Effective Tax Rate | E3: ='MASTER P&L'!I29*100 -> 114.9
A5: Effective Tax Rate = Income Tax Expense ÷ Income Before Taxes × 100
C6: =(ABS('MASTER P&L'!I28/'MASTER P&L'!I27)*100) -> 114.85714
A8: Explanation: the tax expense was larger than the relatively small pre-tax income.
A11: Operating margin is the best measure of underlying performance because it shows how profitable the company’s core operations are before the effects of financing and taxes. It is therefore less affected by changes in financial expenses and the unusually high effective tax rate seen in FY2023.

Sheet Stage6-Q1(1)
A1: Product Category | B1: FY2016 Revenue | C1: FY2023 Revenue | J1: Segment | L1: FY16 | M1: FY17 | N1: FY18 | O1: FY19 | P1: FY20 | Q1: FY21 | R1: FY22 | S1: FY23
A2: Footwear | B2: 10073 | C2: 12470
A3: Apparel | B3: 7264 | C3: 7757 | J3: BY PRODUCT CATEGORY
A4: Acc. & Gear | B4: 1146 | C4: 1200 | J4: Footwear | L4: 10,073.0 | M4: 11,712.0 | N4: 12,272.0 | O4: 13,380.0 | P4: 11,629.0 | Q4: 12,252.0 | R4: 12,831.0 | S4: 12,470.0
A5: Total Net Revenue | B5: 18483 | C5: 21427 | J5: Apparel | L5: 7,264.0 | M5: 8,190.0 | N5: 8,306.0 | O5: 8,865.0 | P5: 7,104.0 | Q5: 7,772.0 | R5: 8,397.0 | S5: 7,757.0
J6: Acc. & Gear | L6: 1,146.0 | M6: 1,316.0 | N6: 1,337.0 | O6: 1,395.0 | P6: 1,111.0 | Q6: 1,210.0 | R6: 1,283.0 | S6: 1,200.0
J7: Footwear | L7: 10,073.0 | M7: 11,712.0 | N7: 12,272.0 | O7: 13,380.0 | P7: 11,629.0 | Q7: 12,252.0 | R7: 12,831.0 | S7: 12,470.0
A8: Product Category | B8: FY2016 Mix | C8: FY2023 Mix | D8: Change | J8: Total | L8: 18,483.0 | M8: 21,218.0 | N8: 21,915.0 | O8: 23,640.0 | P8: 19,844.0 | Q8: 21,234.0 | R8: 22,511.0 | S8: 21,427.0
A9: Footwear | B9: 0.545 | C9: 0.582 | D9: +3.70 pp
A10: Apparel | B10: 0.393 | C10: 0.362 | D10: -3.10 pp
A11: Acc. & Gear | B11: 0.062 | C11: 0.056 | D11: -0.60 pp | J11: BY BRAND
J12: adidas | L12: 16,746.0 | M12: 19,457.0 | N12: 20,271.0 | O12: 21,985.0 | P12: 18,614.0 | Q12: 20,045.0 | R12: 22,511.0 | S12: 21,427.0
J13: Reebok | K13: (1) | L13: 1,737.0 | M13: 1,761.0 | N13: 1,644.0 | O13: 1,655.0 | P13: 1,230.0 | Q13: 1,189.0 | R13: — | S13: —
A14: Brand | B14: FY2016 Revenue | C14: FY2023 Revenue | J14: Total | L14: 18,483.0 | M14: 21,218.0 | N14: 21,915.0 | O14: 23,640.0 | P14: 19,844.0 | Q14: 21,234.0 | R14: 22,511.0 | S14: 21,427.0
A15: adidas | B15: 16746 | C15: 21427
A16: Reebok | B16: 1737 | C16: —
A17: Total | B17: 18483 | C17: 21427
A19: For FY2016: | C19: Therefore, for FY2023:
A20: adidas: | C20: adidas = 100% of reported brand revenue
A21: 16,746/18,483×100=90.60% | C21: Reebok = N/A / Not reported
A22: Reebok:
A23: 1,737/18,483×100=9.40%

Sheet Stage6-Q1(2),Q2
A1: Distribution Channel | B1: FY2016 | C1: FY2023 | D1: Change | H1: BY DISTRIBUTION CHANNEL | I1: FY16 | J1: FY17 | K1: FY18 | L1: FY19 | M1: FY20 | N1: FY21 | O1: FY22 | P1: FY23
A2: Wholesale | B2: =(I2/I5) -> 0.63101228 | C2: =P2/P5 -> 0.51999813 | D2: =C2-B2 -> -0.11101415 | H2: Wholesale | I2: 11,663.0 | J2: 12,943.0 | K2: 12,733.0 | L2: 13,191.0 | M2: 10,160.0 | N2: 11,148.0 | O2: 12,156.0 | P2: 11,142.0
A3: Retail | B3: =I3/I5 -> 0.31602013 | C3: =P3/P5 -> 0.45297989 | D3: =C3-B3 -> 0.13695976 | H3: Retail | I3: 5,841.0 | J3: 7,172.0 | K3: 8,196.0 | L3: 9,480.0 | M3: 8,970.0 | N3: 9,428.0 | O3: 9,725.0 | P3: 9,706.0
A4: Other Businesses | B4: =I4/I5 -> 0.052967592 | C4: =P4/P5 -> 0.027021982 | D4: =C4-B4 -> -0.02594561 | H4: Other Businesses | I4: 979.0 | J4: 1,103.0 | K4: 986.0 | L4: 969.0 | M4: 714.0 | N4: 658.0 | O4: 630.0 | P4: 579.0
A5: Total | B5: =B2+B3+B4 -> 1 | C5: =C2+C3+C4 -> 1 | H5: Total | I5: 18,483.0 | J5: 21,218.0 | K5: 21,915.0 | L5: 23,640.0 | M5: 19,844.0 | N5: 21,234.0 | O5: 22,511.0 | P5: 21,427.0
A8: growth over the period.
A10: Revenue Growth (%)=((FY2023 Revenue−FY2016 Revenue)/FY2016 Revenue)×100
B11: =(('MASTER P&L'!I6-'MASTER P&L'!B6)/'MASTER P&L'!B6)*100 -> 15.92815
A13: Wholesale Growth %=Wholesale FY2023−Wholesale FY2016/Wholesale FY2016×100
B14: =((P2-I2)/I2)*100 -> -4.4671182
A16: Retail Growth %=Retail FY2023−Retail FY2016/Retail FY2016×100
B17: =((P3-I3)/I3)*100 -> 66.170176
A19: Measure | B19: Growth FY2016–FY2023
A20: Total Revenue Growth | B20: 0.1593
A21: Wholesale Growth | B21: -0.0447
A22: Retail Growth | B22: 0.6617

Sheet Stage6-Q4
A1: REPORTED SEGMENTATION - FY2016 to FY2019 | B1: Apply the mapping | E1: Region | F1: 2016 | G1: 2017 | H1: 2018 | I1: 2019 | J1: 2020 | K1: 2021 | L1: 2022 | M1: 2023
A2: Western Europe | E2: EMEA | F2: 7393 | G2: 7956 | H2: 7955 | I2: 8369 | J2: 7005 | K2: 7432 | L2: 7879 | M2: 7585
A3: North America | B3: Old FY2019 region | C3: New comparable region | E3: North America | F3: 3068 | G3: 3947 | H3: 4361 | I3: 4917 | J3: 4127 | K3: 5330 | L3: 5921 | M3: 5142
A4: Grtr China | B4: Western Europe | C4: EMEA | E4: Greater China | F4: 2976 | G4: 3756 | H4: 4164 | I4: 4728 | J4: 4346 | K4: 4247 | L4: 3534 | M4: 3257
A5: Russia / CIS | B5: Russia/CIS | C5: EMEA | E5: Asia-Pacific | F5: 2421 | G5: 2716 | H5: 2761 | I5: 2931 | J5: 2342 | K5: 2060 | L5: 2656 | M5: 2807
A6: Latin America | B6: Emerging Markets | C6: EMEA | E6: Latin America | F6: 1645 | G6: 1740 | H6: 1688 | I6: 1726 | J6: 1310 | K6: 1507 | L6: 1891 | M6: 2057
A7: Other Asian Mkts | B7: North America | C7: North America | E7: Other Businesses | F7: 980 | G7: 1103 | H7: 986 | I7: 969 | J7: 714 | K7: 658 | L7: 630 | M7: 579
A8: Emerging Markets | B8: Greater China | C8: Greater China | E8: Total | F8: 18483 | G8: 21218 | H8: 21915 | I8: 23640 | J8: 19844 | K8: 21234 | L8: 22511 | M8: 21427
A9: Other Businesses | B9: Other Asian Markets | C9: Asia-Pacific
B10: Latin America | C10: Latin America
A11: REPORTED SEGMENTATION - FY2020 to FY2023 | B11: Other Businesses | C11: Other Businesses
A12: EMEA
A13: North America | B13: EMEA = Western Europe + Russia/CIS + Emerging Markets
A14: Greater China
A15: Asia-Pacific | B15: Asia-Pacific = Other Asian Markets
A16: Latin America | B16: All other regions are carried across directly.
A17: Other Businesses

Sheet Stage6-Q5
A1: Region | B1: FY2019 Restated (€mn) | C1: FY2023 (€mn) | D1: Contribution to Revenue Change (€mn)
A2: EMEA | B2: 8369 | C2: 7585 | D2: -784
A3: North America | B3: 4917 | C3: 5142 | D3: 225
A4: Greater China | B4: 4728 | C4: 3257 | D4: -1471
A5: Asia-Pacific | B5: 2931 | C5: 2807 | D5: -124
A6: Latin America | B6: 1726 | C6: 2057 | D6: 331
A7: Other Businesses | B7: 969 | C7: 579 | D7: -390
A8: Total | B8: 23640 | C8: 21427 | D8: -2213
A12: Greater China:
A13: =C4-B4 -> -1471 | B13: EUR mn
A14: So Greater China reduced total revenue by €1,471 million.
A15: Latin America:
A16: =C6-B6 -> 331 | B16: EUR mn
A17: So Latin America added €331 million.

Sheet Stage6-Q6
A1: Revenue per Employee (€’000)=(Revenue (€mn)×1,000)/Employees
A5: Year | B5: Total Revenue (€mn) | C5: Employees (FTE) | D5: Revenue per Employee (€'000)
A6: FY2016 | B6: 18483 | C6: 60617 | D6: =(B6*1000)/C6 -> 304.91446
A7: FY2017 | B7: 21218 | C7: 56888 | D7: =(B7*1000)/C7 -> 372.97848
A8: FY2018 | B8: 21915 | C8: 57016 | D8: =(B8*1000)/C8 -> 384.36579
A9: FY2019 | B9: 23640 | C9: 59533 | D9: =(B9*1000)/C9 -> 397.09069
A10: FY2020 | B10: 19844 | C10: 62285 | D10: =(B10*1000)/C10 -> 318.59998
A11: FY2021 | B11: 21234 | C11: 61401 | D11: =(B11*1000)/C11 -> 345.82499
A12: FY2022 | B12: 22511 | C12: 59258 | D12: =(B12*1000)/C12 -> 379.8812
A13: FY2023 | B13: 21427 | C13: 57069 | D13: =(B13*1000)/C13 -> 375.45778
A15: The highest level was FY2019 at €397.1k per employee. The lowest was FY2016 at €304.9k per employee. There was a significant decline in FY2020, followed by recovery in FY2021 and FY2022. FY2023 saw a small decline from FY2022.

Sheet Formatted Master P&L(Stasge7)
A1: ADS GY Equity — Master P&L
A2: FY2016–FY2023 | EUR mn except per-share data
A3: Line Item | B3: FY2016 | C3: FY2017 | D3: FY2018 | E3: FY2019 | F3: FY2020 | G3: FY2021 | H3: FY2022 | I3: FY2023
A4: REVENUE
A5: Wholesale | B5: {=IF($A5="","",_xlfn.XLOOKUP(1,(Table1[Line Item]=$A5)*(Table1[Fiscal Year]=VALUE(RIGHT(B$3,4))),Table1[Value],"Not found"))} -> 11663 | C5: {=IF($A5="","",_xlfn.XLOOKUP(1,(Table1[Line Item]=$A5)*(Table1[Fiscal Year]=VALUE(RIGHT(C$3,4))),Table1[Value],"Not found"))} -> 12943 | D5: {=IF($A5="","",_xlfn.XLOOKUP(1,(Table1[Line Item]=$A5)*(Table1[Fiscal Year]=VALUE(RIGHT(D$3,4))),Table1[Value],"Not found"))} -> 12733 | E5: {=IF($A5="","",_xlfn.XLOOKUP(1,(Table1[Line Item]=$A5)*(Table1[Fiscal Year]=VALUE(RIGHT(E$3,4))),Table1[Value],"Not found"))} -> 13191 | F5: {=IF($A5="","",_xlfn.XLOOKUP(1,(Table1[Line Item]=$A5)*(Table1[Fiscal Year]=VALUE(RIGHT(F$3,4))),Table1[Value],"Not found"))} -> 10160 | G5: {=IF($A5="","",_xlfn.XLOOKUP(1,(Table1[Line Item]=$A5)*(Table1[Fiscal Year]=VALUE(RIGHT(G$3,4))),Table1[Value],"Not found"))} -> 11148 | H5: {=IF($A5="","",_xlfn.XLOOKUP(1,(Table1[Line Item]=$A5)*(Table1[Fiscal Year]=VALUE(RIGHT(H$3,4))),Table1[Value],"Not found"))} -> 12156 | I5: {=IF($A5="","",_xlfn.XLOOKUP(1,(Table1[Line Item]=$A5)*(Table1[Fiscal Year]=VALUE(RIGHT(I$3,4))),Table1[Value],"Not found"))} -> 11142
A6: Retail | B6: {=IF($A6="","",_xlfn.XLOOKUP(1,(Table1[Line Item]=$A6)*(Table1[Fiscal Year]=VALUE(RIGHT(B$3,4))),Table1[Value],"Not found"))} -> 5841 | C6: {=IF($A6="","",_xlfn.XLOOKUP(1,(Table1[Line Item]=$A6)*(Table1[Fiscal Year]=VALUE(RIGHT(C$3,4))),Table1[Value],"Not found"))} -> 7172 | D6: {=IF($A6="","",_xlfn.XLOOKUP(1,(Table1[Line Item]=$A6)*(Table1[Fiscal Year]=VALUE(RIGHT(D$3,4))),Table1[Value],"Not found"))} -> 8196 | E6: {=IF($A6="","",_xlfn.XLOOKUP(1,(Table1[Line Item]=$A6)*(Table1[Fiscal Year]=VALUE(RIGHT(E$3,4))),Table1[Value],"Not found"))} -> 9480 | F6: {=IF($A6="","",_xlfn.XLOOKUP(1,(Table1[Line Item]=$A6)*(Table1[Fiscal Year]=VALUE(RIGHT(F$3,4))),Table1[Value],"Not found"))} -> 8970 | G6: {=IF($A6="","",_xlfn.XLOOKUP(1,(Table1[Line Item]=$A6)*(Table1[Fiscal Year]=VALUE(RIGHT(G$3,4))),Table1[Value],"Not found"))} -> 9428 | H6: {=IF($A6="","",_xlfn.XLOOKUP(1,(Table1[Line Item]=$A6)*(Table1[Fiscal Year]=VALUE(RIGHT(H$3,4))),Table1[Value],"Not found"))} -> 9725 | I6: {=IF($A6="","",_xlfn.XLOOKUP(1,(Table1[Line Item]=$A6)*(Table1[Fiscal Year]=VALUE(RIGHT(I$3,4))),Table1[Value],"Not found"))} -> 9706
A7: Other Businesses | B7: {=IF($A7="","",_xlfn.XLOOKUP(1,(Table1[Line Item]=$A7)*(Table1[Fiscal Year]=VALUE(RIGHT(B$3,4))),Table1[Value],"Not found"))} -> 979 | C7: {=IF($A7="","",_xlfn.XLOOKUP(1,(Table1[Line Item]=$A7)*(Table1[Fiscal Year]=VALUE(RIGHT(C$3,4))),Table1[Value],"Not found"))} -> 1103 | D7: {=IF($A7="","",_xlfn.XLOOKUP(1,(Table1[Line Item]=$A7)*(Table1[Fiscal Year]=VALUE(RIGHT(D$3,4))),Table1[Value],"Not found"))} -> 986 | E7: {=IF($A7="","",_xlfn.XLOOKUP(1,(Table1[Line Item]=$A7)*(Table1[Fiscal Year]=VALUE(RIGHT(E$3,4))),Table1[Value],"Not found"))} -> 969 | F7: {=IF($A7="","",_xlfn.XLOOKUP(1,(Table1[Line Item]=$A7)*(Table1[Fiscal Year]=VALUE(RIGHT(F$3,4))),Table1[Value],"Not found"))} -> 714 | G7: {=IF($A7="","",_xlfn.XLOOKUP(1,(Table1[Line Item]=$A7)*(Table1[Fiscal Year]=VALUE(RIGHT(G$3,4))),Table1[Value],"Not found"))} -> 658 | H7: {=IF($A7="","",_xlfn.XLOOKUP(1,(Table1[Line Item]=$A7)*(Table1[Fiscal Year]=VALUE(RIGHT(H$3,4))),Table1[Value],"Not found"))} -> 630 | I7: {=IF($A7="","",_xlfn.XLOOKUP(1,(Table1[Line Item]=$A7)*(Table1[Fiscal Year]=VALUE(RIGHT(I$3,4))),Table1[Value],"Not found"))} -> 579
A8: Total Net Revenue | B8: {=IF($A8="","",_xlfn.XLOOKUP(1,(Table1[Line Item]=$A8)*(Table1[Fiscal Year]=VALUE(RIGHT(B$3,4))),Table1[Value],"Not found"))} -> 18483 | C8: {=IF($A8="","",_xlfn.XLOOKUP(1,(Table1[Line Item]=$A8)*(Table1[Fiscal Year]=VALUE(RIGHT(C$3,4))),Table1[Value],"Not found"))} -> 21218 | D8: {=IF($A8="","",_xlfn.XLOOKUP(1,(Table1[Line Item]=$A8)*(Table1[Fiscal Year]=VALUE(RIGHT(D$3,4))),Table1[Value],"Not found"))} -> 21915 | E8: {=IF($A8="","",_xlfn.XLOOKUP(1,(Table1[Line Item]=$A8)*(Table1[Fiscal Year]=VALUE(RIGHT(E$3,4))),Table1[Value],"Not found"))} -> 23640 | F8: {=IF($A8="","",_xlfn.XLOOKUP(1,(Table1[Line Item]=$A8)*(Table1[Fiscal Year]=VALUE(RIGHT(F$3,4))),Table1[Value],"Not found"))} -> 19844 | G8: {=IF($A8="","",_xlfn.XLOOKUP(1,(Table1[Line Item]=$A8)*(Table1[Fiscal Year]=VALUE(RIGHT(G$3,4))),Table1[Value],"Not found"))} -> 21234 | H8: {=IF($A8="","",_xlfn.XLOOKUP(1,(Table1[Line Item]=$A8)*(Table1[Fiscal Year]=VALUE(RIGHT(H$3,4))),Table1[Value],"Not found"))} -> 22511 | I8: {=IF($A8="","",_xlfn.XLOOKUP(1,(Table1[Line Item]=$A8)*(Table1[Fiscal Year]=VALUE(RIGHT(I$3,4))),Table1[Value],"Not found"))} -> 21427
A9: Revenue Growth Y/Y | B9: =(B8/B8)-1 -> 0 | C9: =(C8/B8)-1 -> 0.14797381 | D9: =(D8/C8)-1 -> 0.032849467 | E9: =(E8/D8)-1 -> 0.07871321 | F9: =(F8/E8)-1 -> -0.1605753 | G9: =(G8/F8)-1 -> 0.070046362 | H9: =(H8/G8)-1 -> 0.060139399 | I9: =(I8/H8)-1 -> -0.048154236
A10: GROSS PROFIT
A11: Cost of Goods Sold | B11: {=IF($A11="","",_xlfn.XLOOKUP(1,(Table1[Line Item]=$A11)*(Table1[Fiscal Year]=VALUE(RIGHT(B$3,4))),Table1[Value],"Not found"))} -> -9500 | C11: {=IF($A11="","",_xlfn.XLOOKUP(1,(Table1[Line Item]=$A11)*(Table1[Fiscal Year]=VALUE(RIGHT(C$3,4))),Table1[Value],"Not found"))} -> -10524 | D11: {=IF($A11="","",_xlfn.XLOOKUP(1,(Table1[Line Item]=$A11)*(Table1[Fiscal Year]=VALUE(RIGHT(D$3,4))),Table1[Value],"Not found"))} -> -10607 | E11: {=IF($A11="","",_xlfn.XLOOKUP(1,(Table1[Line Item]=$A11)*(Table1[Fiscal Year]=VALUE(RIGHT(E$3,4))),Table1[Value],"Not found"))} -> -11347 | F11: {=IF($A11="","",_xlfn.XLOOKUP(1,(Table1[Line Item]=$A11)*(Table1[Fiscal Year]=VALUE(RIGHT(F$3,4))),Table1[Value],"Not found"))} -> -9982 | G11: {=IF($A11="","",_xlfn.XLOOKUP(1,(Table1[Line Item]=$A11)*(Table1[Fiscal Year]=VALUE(RIGHT(G$3,4))),Table1[Value],"Not found"))} -> -10511 | H11: {=IF($A11="","",_xlfn.XLOOKUP(1,(Table1[Line Item]=$A11)*(Table1[Fiscal Year]=VALUE(RIGHT(H$3,4))),Table1[Value],"Not found"))} -> -11863 | I11: {=IF($A11="","",_xlfn.XLOOKUP(1,(Table1[Line Item]=$A11)*(Table1[Fiscal Year]=VALUE(RIGHT(I$3,4))),Table1[Value],"Not found"))} -> -11249
A12: Gross Profit | B12: {=IF($A12="","",_xlfn.XLOOKUP(1,(Table1[Line Item]=$A12)*(Table1[Fiscal Year]=VALUE(RIGHT(B$3,4))),Table1[Value],"Not found"))} -> 8983 | C12: {=IF($A12="","",_xlfn.XLOOKUP(1,(Table1[Line Item]=$A12)*(Table1[Fiscal Year]=VALUE(RIGHT(C$3,4))),Table1[Value],"Not found"))} -> 10694 | D12: {=IF($A12="","",_xlfn.XLOOKUP(1,(Table1[Line Item]=$A12)*(Table1[Fiscal Year]=VALUE(RIGHT(D$3,4))),Table1[Value],"Not found"))} -> 11308 | E12: {=IF($A12="","",_xlfn.XLOOKUP(1,(Table1[Line Item]=$A12)*(Table1[Fiscal Year]=VALUE(RIGHT(E$3,4))),Table1[Value],"Not found"))} -> 12293 | F12: {=IF($A12="","",_xlfn.XLOOKUP(1,(Table1[Line Item]=$A12)*(Table1[Fiscal Year]=VALUE(RIGHT(F$3,4))),Table1[Value],"Not found"))} -> 9862 | G12: {=IF($A12="","",_xlfn.XLOOKUP(1,(Table1[Line Item]=$A12)*(Table1[Fiscal Year]=VALUE(RIGHT(G$3,4))),Table1[Value],"Not found"))} -> 10723 | H12: {=IF($A12="","",_xlfn.XLOOKUP(1,(Table1[Line Item]=$A12)*(Table1[Fiscal Year]=VALUE(RIGHT(H$3,4))),Table1[Value],"Not found"))} -> 10648 | I12: {=IF($A12="","",_xlfn.XLOOKUP(1,(Table1[Line Item]=$A12)*(Table1[Fiscal Year]=VALUE(RIGHT(I$3,4))),Table1[Value],"Not found"))} -> 10178
A13: Gross Margin % | B13: =B12/B8 -> 0.48601418 | C13: =C12/C8 -> 0.50400603 | D13: =D12/D8 -> 0.51599361 | E13: =E12/E8 -> 0.52000846 | F13: =F12/F8 -> 0.49697642 | G13: =G12/G8 -> 0.50499199 | H13: =H12/H8 -> 0.47301319 | I13: =I12/I8 -> 0.47500817
A14: OPERATING ITEMS
A15: Royalty and Commission Income | B15: {=IF($A15="","",_xlfn.XLOOKUP(1,(Table1[Line Item]=$A15)*(Table1[Fiscal Year]=VALUE(RIGHT(B$3,4))),Table1[Value],"Not found"))} -> 108 | C15: {=IF($A15="","",_xlfn.XLOOKUP(1,(Table1[Line Item]=$A15)*(Table1[Fiscal Year]=VALUE(RIGHT(C$3,4))),Table1[Value],"Not found"))} -> 115 | D15: {=IF($A15="","",_xlfn.XLOOKUP(1,(Table1[Line Item]=$A15)*(Table1[Fiscal Year]=VALUE(RIGHT(D$3,4))),Table1[Value],"Not found"))} -> 121 | E15: {=IF($A15="","",_xlfn.XLOOKUP(1,(Table1[Line Item]=$A15)*(Table1[Fiscal Year]=VALUE(RIGHT(E$3,4))),Table1[Value],"Not found"))} -> 130 | F15: {=IF($A15="","",_xlfn.XLOOKUP(1,(Table1[Line Item]=$A15)*(Table1[Fiscal Year]=VALUE(RIGHT(F$3,4))),Table1[Value],"Not found"))} -> 96 | G15: {=IF($A15="","",_xlfn.XLOOKUP(1,(Table1[Line Item]=$A15)*(Table1[Fiscal Year]=VALUE(RIGHT(G$3,4))),Table1[Value],"Not found"))} -> 104 | H15: {=IF($A15="","",_xlfn.XLOOKUP(1,(Table1[Line Item]=$A15)*(Table1[Fiscal Year]=VALUE(RIGHT(H$3,4))),Table1[Value],"Not found"))} -> 112 | I15: {=IF($A15="","",_xlfn.XLOOKUP(1,(Table1[Line Item]=$A15)*(Table1[Fiscal Year]=VALUE(RIGHT(I$3,4))),Table1[Value],"Not found"))} -> 107
A16: Other Operating Income | B16: {=IF($A16="","",_xlfn.XLOOKUP(1,(Table1[Line Item]=$A16)*(Table1[Fiscal Year]=VALUE(RIGHT(B$3,4))),Table1[Value],"Not found"))} -> 60 | C16: {=IF($A16="","",_xlfn.XLOOKUP(1,(Table1[Line Item]=$A16)*(Table1[Fiscal Year]=VALUE(RIGHT(C$3,4))),Table1[Value],"Not found"))} -> 66 | D16: {=IF($A16="","",_xlfn.XLOOKUP(1,(Table1[Line Item]=$A16)*(Table1[Fiscal Year]=VALUE(RIGHT(D$3,4))),Table1[Value],"Not found"))} -> 71 | E16: {=IF($A16="","",_xlfn.XLOOKUP(1,(Table1[Line Item]=$A16)*(Table1[Fiscal Year]=VALUE(RIGHT(E$3,4))),Table1[Value],"Not found"))} -> 78 | F16: {=IF($A16="","",_xlfn.XLOOKUP(1,(Table1[Line Item]=$A16)*(Table1[Fiscal Year]=VALUE(RIGHT(F$3,4))),Table1[Value],"Not found"))} -> 52 | G16: {=IF($A16="","",_xlfn.XLOOKUP(1,(Table1[Line Item]=$A16)*(Table1[Fiscal Year]=VALUE(RIGHT(G$3,4))),Table1[Value],"Not found"))} -> 58 | H16: {=IF($A16="","",_xlfn.XLOOKUP(1,(Table1[Line Item]=$A16)*(Table1[Fiscal Year]=VALUE(RIGHT(H$3,4))),Table1[Value],"Not found"))} -> 63 | I16: {=IF($A16="","",_xlfn.XLOOKUP(1,(Table1[Line Item]=$A16)*(Table1[Fiscal Year]=VALUE(RIGHT(I$3,4))),Table1[Value],"Not found"))} -> 55
A17: Marketing and Point-of-Sale | B17: {=IF($A17="","",_xlfn.XLOOKUP(1,(Table1[Line Item]=$A17)*(Table1[Fiscal Year]=VALUE(RIGHT(B$3,4))),Table1[Value],"Not found"))} -> -2532 | C17: {=IF($A17="","",_xlfn.XLOOKUP(1,(Table1[Line Item]=$A17)*(Table1[Fiscal Year]=VALUE(RIGHT(C$3,4))),Table1[Value],"Not found"))} -> -2843 | D17: {=IF($A17="","",_xlfn.XLOOKUP(1,(Table1[Line Item]=$A17)*(Table1[Fiscal Year]=VALUE(RIGHT(D$3,4))),Table1[Value],"Not found"))} -> -2871 | E17: {=IF($A17="","",_xlfn.XLOOKUP(1,(Table1[Line Item]=$A17)*(Table1[Fiscal Year]=VALUE(RIGHT(E$3,4))),Table1[Value],"Not found"))} -> -3026 | F17: {=IF($A17="","",_xlfn.XLOOKUP(1,(Table1[Line Item]=$A17)*(Table1[Fiscal Year]=VALUE(RIGHT(F$3,4))),Table1[Value],"Not found"))} -> -2361 | G17: {=IF($A17="","",_xlfn.XLOOKUP(1,(Table1[Line Item]=$A17)*(Table1[Fiscal Year]=VALUE(RIGHT(G$3,4))),Table1[Value],"Not found"))} -> -2569 | H17: {=IF($A17="","",_xlfn.XLOOKUP(1,(Table1[Line Item]=$A17)*(Table1[Fiscal Year]=VALUE(RIGHT(H$3,4))),Table1[Value],"Not found"))} -> -2791 | I17: {=IF($A17="","",_xlfn.XLOOKUP(1,(Table1[Line Item]=$A17)*(Table1[Fiscal Year]=VALUE(RIGHT(I$3,4))),Table1[Value],"Not found"))} -> -2636
A18: Distribution and Selling Expense | B18: {=IF($A18="","",_xlfn.XLOOKUP(1,(Table1[Line Item]=$A18)*(Table1[Fiscal Year]=VALUE(RIGHT(B$3,4))),Table1[Value],"Not found"))} -> -4029 | C18: {=IF($A18="","",_xlfn.XLOOKUP(1,(Table1[Line Item]=$A18)*(Table1[Fiscal Year]=VALUE(RIGHT(C$3,4))),Table1[Value],"Not found"))} -> -4710 | D18: {=IF($A18="","",_xlfn.XLOOKUP(1,(Table1[Line Item]=$A18)*(Table1[Fiscal Year]=VALUE(RIGHT(D$3,4))),Table1[Value],"Not found"))} -> -4909 | E18: {=IF($A18="","",_xlfn.XLOOKUP(1,(Table1[Line Item]=$A18)*(Table1[Fiscal Year]=VALUE(RIGHT(E$3,4))),Table1[Value],"Not found"))} -> -5272 | F18: {=IF($A18="","",_xlfn.XLOOKUP(1,(Table1[Line Item]=$A18)*(Table1[Fiscal Year]=VALUE(RIGHT(F$3,4))),Table1[Value],"Not found"))} -> -5358 | G18: {=IF($A18="","",_xlfn.XLOOKUP(1,(Table1[Line Item]=$A18)*(Table1[Fiscal Year]=VALUE(RIGHT(G$3,4))),Table1[Value],"Not found"))} -> -4969 | H18: {=IF($A18="","",_xlfn.XLOOKUP(1,(Table1[Line Item]=$A18)*(Table1[Fiscal Year]=VALUE(RIGHT(H$3,4))),Table1[Value],"Not found"))} -> -5470 | I18: {=IF($A18="","",_xlfn.XLOOKUP(1,(Table1[Line Item]=$A18)*(Table1[Fiscal Year]=VALUE(RIGHT(I$3,4))),Table1[Value],"Not found"))} -> -5528
A19: General & Administration | B19: {=IF($A19="","",_xlfn.XLOOKUP(1,(Table1[Line Item]=$A19)*(Table1[Fiscal Year]=VALUE(RIGHT(B$3,4))),Table1[Value],"Not found"))} -> -998 | C19: {=IF($A19="","",_xlfn.XLOOKUP(1,(Table1[Line Item]=$A19)*(Table1[Fiscal Year]=VALUE(RIGHT(C$3,4))),Table1[Value],"Not found"))} -> -1125 | D19: {=IF($A19="","",_xlfn.XLOOKUP(1,(Table1[Line Item]=$A19)*(Table1[Fiscal Year]=VALUE(RIGHT(D$3,4))),Table1[Value],"Not found"))} -> -1140 | E19: {=IF($A19="","",_xlfn.XLOOKUP(1,(Table1[Line Item]=$A19)*(Table1[Fiscal Year]=VALUE(RIGHT(E$3,4))),Table1[Value],"Not found"))} -> -1347 | F19: {=IF($A19="","",_xlfn.XLOOKUP(1,(Table1[Line Item]=$A19)*(Table1[Fiscal Year]=VALUE(RIGHT(F$3,4))),Table1[Value],"Not found"))} -> -1290 | G19: {=IF($A19="","",_xlfn.XLOOKUP(1,(Table1[Line Item]=$A19)*(Table1[Fiscal Year]=VALUE(RIGHT(G$3,4))),Table1[Value],"Not found"))} -> -1295 | H19: {=IF($A19="","",_xlfn.XLOOKUP(1,(Table1[Line Item]=$A19)*(Table1[Fiscal Year]=VALUE(RIGHT(H$3,4))),Table1[Value],"Not found"))} -> -1756 | I19: {=IF($A19="","",_xlfn.XLOOKUP(1,(Table1[Line Item]=$A19)*(Table1[Fiscal Year]=VALUE(RIGHT(I$3,4))),Table1[Value],"Not found"))} -> -1564
A20: Sundry Expenses | B20: {=IF($A20="","",_xlfn.XLOOKUP(1,(Table1[Line Item]=$A20)*(Table1[Fiscal Year]=VALUE(RIGHT(B$3,4))),Table1[Value],"Not found"))} -> -185 | C20: {=IF($A20="","",_xlfn.XLOOKUP(1,(Table1[Line Item]=$A20)*(Table1[Fiscal Year]=VALUE(RIGHT(C$3,4))),Table1[Value],"Not found"))} -> -212 | D20: {=IF($A20="","",_xlfn.XLOOKUP(1,(Table1[Line Item]=$A20)*(Table1[Fiscal Year]=VALUE(RIGHT(D$3,4))),Table1[Value],"Not found"))} -> -219 | E20: {=IF($A20="","",_xlfn.XLOOKUP(1,(Table1[Line Item]=$A20)*(Table1[Fiscal Year]=VALUE(RIGHT(E$3,4))),Table1[Value],"Not found"))} -> -236 | F20: {=IF($A20="","",_xlfn.XLOOKUP(1,(Table1[Line Item]=$A20)*(Table1[Fiscal Year]=VALUE(RIGHT(F$3,4))),Table1[Value],"Not found"))} -> -198 | G20: {=IF($A20="","",_xlfn.XLOOKUP(1,(Table1[Line Item]=$A20)*(Table1[Fiscal Year]=VALUE(RIGHT(G$3,4))),Table1[Value],"Not found"))} -> -212 | H20: {=IF($A20="","",_xlfn.XLOOKUP(1,(Table1[Line Item]=$A20)*(Table1[Fiscal Year]=VALUE(RIGHT(H$3,4))),Table1[Value],"Not found"))} -> -225 | I20: {=IF($A20="","",_xlfn.XLOOKUP(1,(Table1[Line Item]=$A20)*(Table1[Fiscal Year]=VALUE(RIGHT(I$3,4))),Table1[Value],"Not found"))} -> -257
A21: Total Other Operating Exp. | B21: {=IF($A21="","",_xlfn.XLOOKUP(1,(Table1[Line Item]=$A21)*(Table1[Fiscal Year]=VALUE(RIGHT(B$3,4))),Table1[Value],"Not found"))} -> -7744 | C21: {=IF($A21="","",_xlfn.XLOOKUP(1,(Table1[Line Item]=$A21)*(Table1[Fiscal Year]=VALUE(RIGHT(C$3,4))),Table1[Value],"Not found"))} -> -8890 | D21: {=IF($A21="","",_xlfn.XLOOKUP(1,(Table1[Line Item]=$A21)*(Table1[Fiscal Year]=VALUE(RIGHT(D$3,4))),Table1[Value],"Not found"))} -> -9139 | E21: {=IF($A21="","",_xlfn.XLOOKUP(1,(Table1[Line Item]=$A21)*(Table1[Fiscal Year]=VALUE(RIGHT(E$3,4))),Table1[Value],"Not found"))} -> -9881 | F21: {=IF($A21="","",_xlfn.XLOOKUP(1,(Table1[Line Item]=$A21)*(Table1[Fiscal Year]=VALUE(RIGHT(F$3,4))),Table1[Value],"Not found"))} -> -9207 | G21: {=IF($A21="","",_xlfn.XLOOKUP(1,(Table1[Line Item]=$A21)*(Table1[Fiscal Year]=VALUE(RIGHT(G$3,4))),Table1[Value],"Not found"))} -> -9045 | H21: {=IF($A21="","",_xlfn.XLOOKUP(1,(Table1[Line Item]=$A21)*(Table1[Fiscal Year]=VALUE(RIGHT(H$3,4))),Table1[Value],"Not found"))} -> -10242 | I21: {=IF($A21="","",_xlfn.XLOOKUP(1,(Table1[Line Item]=$A21)*(Table1[Fiscal Year]=VALUE(RIGHT(I$3,4))),Table1[Value],"Not found"))} -> -9985
A22: Goodwill / Intangible Impairment | B22: {=IF($A22="","",_xlfn.XLOOKUP(1,(Table1[Line Item]=$A22)*(Table1[Fiscal Year]=VALUE(RIGHT(B$3,4))),Table1[Value],"Not found"))} -> 0 | C22: {=IF($A22="","",_xlfn.XLOOKUP(1,(Table1[Line Item]=$A22)*(Table1[Fiscal Year]=VALUE(RIGHT(C$3,4))),Table1[Value],"Not found"))} -> 0 | D22: {=IF($A22="","",_xlfn.XLOOKUP(1,(Table1[Line Item]=$A22)*(Table1[Fiscal Year]=VALUE(RIGHT(D$3,4))),Table1[Value],"Not found"))} -> 0 | E22: {=IF($A22="","",_xlfn.XLOOKUP(1,(Table1[Line Item]=$A22)*(Table1[Fiscal Year]=VALUE(RIGHT(E$3,4))),Table1[Value],"Not found"))} -> 0 | F22: {=IF($A22="","",_xlfn.XLOOKUP(1,(Table1[Line Item]=$A22)*(Table1[Fiscal Year]=VALUE(RIGHT(F$3,4))),Table1[Value],"Not found"))} -> 0 | G22: {=IF($A22="","",_xlfn.XLOOKUP(1,(Table1[Line Item]=$A22)*(Table1[Fiscal Year]=VALUE(RIGHT(G$3,4))),Table1[Value],"Not found"))} -> 0 | H22: {=IF($A22="","",_xlfn.XLOOKUP(1,(Table1[Line Item]=$A22)*(Table1[Fiscal Year]=VALUE(RIGHT(H$3,4))),Table1[Value],"Not found"))} -> -194 | I22: {=IF($A22="","",_xlfn.XLOOKUP(1,(Table1[Line Item]=$A22)*(Table1[Fiscal Year]=VALUE(RIGHT(I$3,4))),Table1[Value],"Not found"))} -> 0
A23: Operating Profit (EBIT) | B23: {=IF($A23="","",_xlfn.XLOOKUP(1,(Table1[Line Item]=$A23)*(Table1[Fiscal Year]=VALUE(RIGHT(B$3,4))),Table1[Value],"Not found"))} -> 1407 | C23: {=IF($A23="","",_xlfn.XLOOKUP(1,(Table1[Line Item]=$A23)*(Table1[Fiscal Year]=VALUE(RIGHT(C$3,4))),Table1[Value],"Not found"))} -> 1985 | D23: {=IF($A23="","",_xlfn.XLOOKUP(1,(Table1[Line Item]=$A23)*(Table1[Fiscal Year]=VALUE(RIGHT(D$3,4))),Table1[Value],"Not found"))} -> 2361 | E23: {=IF($A23="","",_xlfn.XLOOKUP(1,(Table1[Line Item]=$A23)*(Table1[Fiscal Year]=VALUE(RIGHT(E$3,4))),Table1[Value],"Not found"))} -> 2620 | F23: {=IF($A23="","",_xlfn.XLOOKUP(1,(Table1[Line Item]=$A23)*(Table1[Fiscal Year]=VALUE(RIGHT(F$3,4))),Table1[Value],"Not found"))} -> 803 | G23: {=IF($A23="","",_xlfn.XLOOKUP(1,(Table1[Line Item]=$A23)*(Table1[Fiscal Year]=VALUE(RIGHT(G$3,4))),Table1[Value],"Not found"))} -> 1840 | H23: {=IF($A23="","",_xlfn.XLOOKUP(1,(Table1[Line Item]=$A23)*(Table1[Fiscal Year]=VALUE(RIGHT(H$3,4))),Table1[Value],"Not found"))} -> 387 | I23: {=IF($A23="","",_xlfn.XLOOKUP(1,(Table1[Line Item]=$A23)*(Table1[Fiscal Year]=VALUE(RIGHT(I$3,4))),Table1[Value],"Not found"))} -> 355
A24: Operating Margin % | B24: =B23/B8 -> 0.076124006 | C24: =C23/C8 -> 0.093552644 | D24: =D23/D8 -> 0.10773443 | E24: =E23/E8 -> 0.1108291 | F24: =F23/F8 -> 0.040465632 | G24: =G23/G8 -> 0.08665348 | H24: =H23/H8 -> 0.017191595 | I24: =I23/I8 -> 0.016567882
A25: BELOW EBIT
A26: Financial Income | B26: {=IF($A26="","",_xlfn.XLOOKUP(1,(Table1[Line Item]=$A26)*(Table1[Fiscal Year]=VALUE(RIGHT(B$3,4))),Table1[Value],"Not found"))} -> 20 | C26: {=IF($A26="","",_xlfn.XLOOKUP(1,(Table1[Line Item]=$A26)*(Table1[Fiscal Year]=VALUE(RIGHT(C$3,4))),Table1[Value],"Not found"))} -> 24 | D26: {=IF($A26="","",_xlfn.XLOOKUP(1,(Table1[Line Item]=$A26)*(Table1[Fiscal Year]=VALUE(RIGHT(D$3,4))),Table1[Value],"Not found"))} -> 28 | E26: {=IF($A26="","",_xlfn.XLOOKUP(1,(Table1[Line Item]=$A26)*(Table1[Fiscal Year]=VALUE(RIGHT(E$3,4))),Table1[Value],"Not found"))} -> 32 | F26: {=IF($A26="","",_xlfn.XLOOKUP(1,(Table1[Line Item]=$A26)*(Table1[Fiscal Year]=VALUE(RIGHT(F$3,4))),Table1[Value],"Not found"))} -> 26 | G26: {=IF($A26="","",_xlfn.XLOOKUP(1,(Table1[Line Item]=$A26)*(Table1[Fiscal Year]=VALUE(RIGHT(G$3,4))),Table1[Value],"Not found"))} -> 30 | H26: {=IF($A26="","",_xlfn.XLOOKUP(1,(Table1[Line Item]=$A26)*(Table1[Fiscal Year]=VALUE(RIGHT(H$3,4))),Table1[Value],"Not found"))} -> 44 | I26: {=IF($A26="","",_xlfn.XLOOKUP(1,(Table1[Line Item]=$A26)*(Table1[Fiscal Year]=VALUE(RIGHT(I$3,4))),Table1[Value],"Not found"))} -> 62
A27: Financial Expenses | B27: {=IF($A27="","",_xlfn.XLOOKUP(1,(Table1[Line Item]=$A27)*(Table1[Fiscal Year]=VALUE(RIGHT(B$3,4))),Table1[Value],"Not found"))} -> -74 | C27: {=IF($A27="","",_xlfn.XLOOKUP(1,(Table1[Line Item]=$A27)*(Table1[Fiscal Year]=VALUE(RIGHT(C$3,4))),Table1[Value],"Not found"))} -> -82 | D27: {=IF($A27="","",_xlfn.XLOOKUP(1,(Table1[Line Item]=$A27)*(Table1[Fiscal Year]=VALUE(RIGHT(D$3,4))),Table1[Value],"Not found"))} -> -91 | E27: {=IF($A27="","",_xlfn.XLOOKUP(1,(Table1[Line Item]=$A27)*(Table1[Fiscal Year]=VALUE(RIGHT(E$3,4))),Table1[Value],"Not found"))} -> -166 | F27: {=IF($A27="","",_xlfn.XLOOKUP(1,(Table1[Line Item]=$A27)*(Table1[Fiscal Year]=VALUE(RIGHT(F$3,4))),Table1[Value],"Not found"))} -> -178 | G27: {=IF($A27="","",_xlfn.XLOOKUP(1,(Table1[Line Item]=$A27)*(Table1[Fiscal Year]=VALUE(RIGHT(G$3,4))),Table1[Value],"Not found"))} -> -172 | H27: {=IF($A27="","",_xlfn.XLOOKUP(1,(Table1[Line Item]=$A27)*(Table1[Fiscal Year]=VALUE(RIGHT(H$3,4))),Table1[Value],"Not found"))} -> -199 | I27: {=IF($A27="","",_xlfn.XLOOKUP(1,(Table1[Line Item]=$A27)*(Table1[Fiscal Year]=VALUE(RIGHT(I$3,4))),Table1[Value],"Not found"))} -> -242
A28: Income Before Taxes | B28: {=IF($A28="","",_xlfn.XLOOKUP(1,(Table1[Line Item]=$A28)*(Table1[Fiscal Year]=VALUE(RIGHT(B$3,4))),Table1[Value],"Not found"))} -> 1353 | C28: {=IF($A28="","",_xlfn.XLOOKUP(1,(Table1[Line Item]=$A28)*(Table1[Fiscal Year]=VALUE(RIGHT(C$3,4))),Table1[Value],"Not found"))} -> 1927 | D28: {=IF($A28="","",_xlfn.XLOOKUP(1,(Table1[Line Item]=$A28)*(Table1[Fiscal Year]=VALUE(RIGHT(D$3,4))),Table1[Value],"Not found"))} -> 2298 | E28: {=IF($A28="","",_xlfn.XLOOKUP(1,(Table1[Line Item]=$A28)*(Table1[Fiscal Year]=VALUE(RIGHT(E$3,4))),Table1[Value],"Not found"))} -> 2486 | F28: {=IF($A28="","",_xlfn.XLOOKUP(1,(Table1[Line Item]=$A28)*(Table1[Fiscal Year]=VALUE(RIGHT(F$3,4))),Table1[Value],"Not found"))} -> 651 | G28: {=IF($A28="","",_xlfn.XLOOKUP(1,(Table1[Line Item]=$A28)*(Table1[Fiscal Year]=VALUE(RIGHT(G$3,4))),Table1[Value],"Not found"))} -> 1698 | H28: {=IF($A28="","",_xlfn.XLOOKUP(1,(Table1[Line Item]=$A28)*(Table1[Fiscal Year]=VALUE(RIGHT(H$3,4))),Table1[Value],"Not found"))} -> 232 | I28: {=IF($A28="","",_xlfn.XLOOKUP(1,(Table1[Line Item]=$A28)*(Table1[Fiscal Year]=VALUE(RIGHT(I$3,4))),Table1[Value],"Not found"))} -> 175
A29: Income Tax Expense | B29: {=IF($A29="","",_xlfn.XLOOKUP(1,(Table1[Line Item]=$A29)*(Table1[Fiscal Year]=VALUE(RIGHT(B$3,4))),Table1[Value],"Not found"))} -> -392 | C29: {=IF($A29="","",_xlfn.XLOOKUP(1,(Table1[Line Item]=$A29)*(Table1[Fiscal Year]=VALUE(RIGHT(C$3,4))),Table1[Value],"Not found"))} -> -540 | D29: {=IF($A29="","",_xlfn.XLOOKUP(1,(Table1[Line Item]=$A29)*(Table1[Fiscal Year]=VALUE(RIGHT(D$3,4))),Table1[Value],"Not found"))} -> -597 | E29: {=IF($A29="","",_xlfn.XLOOKUP(1,(Table1[Line Item]=$A29)*(Table1[Fiscal Year]=VALUE(RIGHT(E$3,4))),Table1[Value],"Not found"))} -> -622 | F29: {=IF($A29="","",_xlfn.XLOOKUP(1,(Table1[Line Item]=$A29)*(Table1[Fiscal Year]=VALUE(RIGHT(F$3,4))),Table1[Value],"Not found"))} -> -228 | G29: {=IF($A29="","",_xlfn.XLOOKUP(1,(Table1[Line Item]=$A29)*(Table1[Fiscal Year]=VALUE(RIGHT(G$3,4))),Table1[Value],"Not found"))} -> -475 | H29: {=IF($A29="","",_xlfn.XLOOKUP(1,(Table1[Line Item]=$A29)*(Table1[Fiscal Year]=VALUE(RIGHT(H$3,4))),Table1[Value],"Not found"))} -> -174 | I29: {=IF($A29="","",_xlfn.XLOOKUP(1,(Table1[Line Item]=$A29)*(Table1[Fiscal Year]=VALUE(RIGHT(I$3,4))),Table1[Value],"Not found"))} -> -201
A30: Effective Tax Rate % | B30: =ABS(B29/B28) -> 0.28972653 | C30: =ABS(C29/C28) -> 0.28022833 | D30: =ABS(D29/D28) -> 0.25979112 | E30: =ABS(E29/E28) -> 0.25020113 | F30: =ABS(F29/F28) -> 0.35023041 | G30: =ABS(G29/G28) -> 0.27974087 | H30: =ABS(H29/H28) -> 0.75 | I30: =ABS(I29/I28) -> 1.1485714
A31: NET INCOME
A32: Net Income from Continuing Ops. | B32: {=IF($A32="","",_xlfn.XLOOKUP(1,(Table1[Line Item]=$A32)*(Table1[Fiscal Year]=VALUE(RIGHT(B$3,4))),Table1[Value],"Not found"))} -> 961 | C32: {=IF($A32="","",_xlfn.XLOOKUP(1,(Table1[Line Item]=$A32)*(Table1[Fiscal Year]=VALUE(RIGHT(C$3,4))),Table1[Value],"Not found"))} -> 1387 | D32: {=IF($A32="","",_xlfn.XLOOKUP(1,(Table1[Line Item]=$A32)*(Table1[Fiscal Year]=VALUE(RIGHT(D$3,4))),Table1[Value],"Not found"))} -> 1701 | E32: {=IF($A32="","",_xlfn.XLOOKUP(1,(Table1[Line Item]=$A32)*(Table1[Fiscal Year]=VALUE(RIGHT(E$3,4))),Table1[Value],"Not found"))} -> 1864 | F32: {=IF($A32="","",_xlfn.XLOOKUP(1,(Table1[Line Item]=$A32)*(Table1[Fiscal Year]=VALUE(RIGHT(F$3,4))),Table1[Value],"Not found"))} -> 423 | G32: {=IF($A32="","",_xlfn.XLOOKUP(1,(Table1[Line Item]=$A32)*(Table1[Fiscal Year]=VALUE(RIGHT(G$3,4))),Table1[Value],"Not found"))} -> 1223 | H32: {=IF($A32="","",_xlfn.XLOOKUP(1,(Table1[Line Item]=$A32)*(Table1[Fiscal Year]=VALUE(RIGHT(H$3,4))),Table1[Value],"Not found"))} -> 58 | I32: {=IF($A32="","",_xlfn.XLOOKUP(1,(Table1[Line Item]=$A32)*(Table1[Fiscal Year]=VALUE(RIGHT(I$3,4))),Table1[Value],"Not found"))} -> -26
A33: Net Income (Total) | B33: {=IF($A33="","",_xlfn.XLOOKUP(1,(Table1[Line Item]=$A33)*(Table1[Fiscal Year]=VALUE(RIGHT(B$3,4))),Table1[Value],"Not found"))} -> 961 | C33: {=IF($A33="","",_xlfn.XLOOKUP(1,(Table1[Line Item]=$A33)*(Table1[Fiscal Year]=VALUE(RIGHT(C$3,4))),Table1[Value],"Not found"))} -> 1387 | D33: {=IF($A33="","",_xlfn.XLOOKUP(1,(Table1[Line Item]=$A33)*(Table1[Fiscal Year]=VALUE(RIGHT(D$3,4))),Table1[Value],"Not found"))} -> 1701 | E33: {=IF($A33="","",_xlfn.XLOOKUP(1,(Table1[Line Item]=$A33)*(Table1[Fiscal Year]=VALUE(RIGHT(E$3,4))),Table1[Value],"Not found"))} -> 1864 | F33: {=IF($A33="","",_xlfn.XLOOKUP(1,(Table1[Line Item]=$A33)*(Table1[Fiscal Year]=VALUE(RIGHT(F$3,4))),Table1[Value],"Not found"))} -> 353 | G33: {=IF($A33="","",_xlfn.XLOOKUP(1,(Table1[Line Item]=$A33)*(Table1[Fiscal Year]=VALUE(RIGHT(G$3,4))),Table1[Value],"Not found"))} -> 1455 | H33: {=IF($A33="","",_xlfn.XLOOKUP(1,(Table1[Line Item]=$A33)*(Table1[Fiscal Year]=VALUE(RIGHT(H$3,4))),Table1[Value],"Not found"))} -> 58 | I33: {=IF($A33="","",_xlfn.XLOOKUP(1,(Table1[Line Item]=$A33)*(Table1[Fiscal Year]=VALUE(RIGHT(I$3,4))),Table1[Value],"Not found"))} -> -26
A34: Less: Minority Interest | B34: {=IF($A34="","",_xlfn.XLOOKUP(1,(Table1[Line Item]=$A34)*(Table1[Fiscal Year]=VALUE(RIGHT(B$3,4))),Table1[Value],"Not found"))} -> -12 | C34: {=IF($A34="","",_xlfn.XLOOKUP(1,(Table1[Line Item]=$A34)*(Table1[Fiscal Year]=VALUE(RIGHT(C$3,4))),Table1[Value],"Not found"))} -> -14 | D34: {=IF($A34="","",_xlfn.XLOOKUP(1,(Table1[Line Item]=$A34)*(Table1[Fiscal Year]=VALUE(RIGHT(D$3,4))),Table1[Value],"Not found"))} -> -11 | E34: {=IF($A34="","",_xlfn.XLOOKUP(1,(Table1[Line Item]=$A34)*(Table1[Fiscal Year]=VALUE(RIGHT(E$3,4))),Table1[Value],"Not found"))} -> -9 | F34: {=IF($A34="","",_xlfn.XLOOKUP(1,(Table1[Line Item]=$A34)*(Table1[Fiscal Year]=VALUE(RIGHT(F$3,4))),Table1[Value],"Not found"))} -> -6 | G34: {=IF($A34="","",_xlfn.XLOOKUP(1,(Table1[Line Item]=$A34)*(Table1[Fiscal Year]=VALUE(RIGHT(G$3,4))),Table1[Value],"Not found"))} -> -8 | H34: {=IF($A34="","",_xlfn.XLOOKUP(1,(Table1[Line Item]=$A34)*(Table1[Fiscal Year]=VALUE(RIGHT(H$3,4))),Table1[Value],"Not found"))} -> -8 | I34: {=IF($A34="","",_xlfn.XLOOKUP(1,(Table1[Line Item]=$A34)*(Table1[Fiscal Year]=VALUE(RIGHT(I$3,4))),Table1[Value],"Not found"))} -> -7
A35: Net Income Attrib. to Shareholders | B35: {=IF($A35="","",_xlfn.XLOOKUP(1,(Table1[Line Item]=$A35)*(Table1[Fiscal Year]=VALUE(RIGHT(B$3,4))),Table1[Value],"Not found"))} -> 949 | C35: {=IF($A35="","",_xlfn.XLOOKUP(1,(Table1[Line Item]=$A35)*(Table1[Fiscal Year]=VALUE(RIGHT(C$3,4))),Table1[Value],"Not found"))} -> 1373 | D35: {=IF($A35="","",_xlfn.XLOOKUP(1,(Table1[Line Item]=$A35)*(Table1[Fiscal Year]=VALUE(RIGHT(D$3,4))),Table1[Value],"Not found"))} -> 1690 | E35: {=IF($A35="","",_xlfn.XLOOKUP(1,(Table1[Line Item]=$A35)*(Table1[Fiscal Year]=VALUE(RIGHT(E$3,4))),Table1[Value],"Not found"))} -> 1855 | F35: {=IF($A35="","",_xlfn.XLOOKUP(1,(Table1[Line Item]=$A35)*(Table1[Fiscal Year]=VALUE(RIGHT(F$3,4))),Table1[Value],"Not found"))} -> 347 | G35: {=IF($A35="","",_xlfn.XLOOKUP(1,(Table1[Line Item]=$A35)*(Table1[Fiscal Year]=VALUE(RIGHT(G$3,4))),Table1[Value],"Not found"))} -> 1447 | H35: {=IF($A35="","",_xlfn.XLOOKUP(1,(Table1[Line Item]=$A35)*(Table1[Fiscal Year]=VALUE(RIGHT(H$3,4))),Table1[Value],"Not found"))} -> 50 | I35: {=IF($A35="","",_xlfn.XLOOKUP(1,(Table1[Line Item]=$A35)*(Table1[Fiscal Year]=VALUE(RIGHT(I$3,4))),Table1[Value],"Not found"))} -> -33
A36: Net Margin % | B36: =(B35/B8) -> 0.051344479 | C36: =(C35/C8) -> 0.064709209 | D36: =(D35/D8) -> 0.077116131 | E36: =(E35/E8) -> 0.078468697 | F36: =(F35/F8) -> 0.017486394 | G36: =(G35/G8) -> 0.068145427 | H36: =(H35/H8) -> 0.0022211363 | I36: =(I35/I8) -> -0.0015401129
A37: PER SHARE
A38: Basic EPS | B38: {=IF($A38="","",_xlfn.XLOOKUP(1,(Table1[Line Item]=$A38)*(Table1[Fiscal Year]=VALUE(RIGHT(B$3,4))),Table1[Value],"Not found"))} -> 4.72 | C38: {=IF($A38="","",_xlfn.XLOOKUP(1,(Table1[Line Item]=$A38)*(Table1[Fiscal Year]=VALUE(RIGHT(C$3,4))),Table1[Value],"Not found"))} -> 6.78 | D38: {=IF($A38="","",_xlfn.XLOOKUP(1,(Table1[Line Item]=$A38)*(Table1[Fiscal Year]=VALUE(RIGHT(D$3,4))),Table1[Value],"Not found"))} -> 8.45 | E38: {=IF($A38="","",_xlfn.XLOOKUP(1,(Table1[Line Item]=$A38)*(Table1[Fiscal Year]=VALUE(RIGHT(E$3,4))),Table1[Value],"Not found"))} -> 9.48 | F38: {=IF($A38="","",_xlfn.XLOOKUP(1,(Table1[Line Item]=$A38)*(Table1[Fiscal Year]=VALUE(RIGHT(F$3,4))),Table1[Value],"Not found"))} -> 1.79 | G38: {=IF($A38="","",_xlfn.XLOOKUP(1,(Table1[Line Item]=$A38)*(Table1[Fiscal Year]=VALUE(RIGHT(G$3,4))),Table1[Value],"Not found"))} -> 7.39 | H38: {=IF($A38="","",_xlfn.XLOOKUP(1,(Table1[Line Item]=$A38)*(Table1[Fiscal Year]=VALUE(RIGHT(H$3,4))),Table1[Value],"Not found"))} -> 0.27 | I38: {=IF($A38="","",_xlfn.XLOOKUP(1,(Table1[Line Item]=$A38)*(Table1[Fiscal Year]=VALUE(RIGHT(I$3,4))),Table1[Value],"Not found"))} -> -0.18
A39: Diluted EPS | B39: {=IF($A39="","",_xlfn.XLOOKUP(1,(Table1[Line Item]=$A39)*(Table1[Fiscal Year]=VALUE(RIGHT(B$3,4))),Table1[Value],"Not found"))} -> 4.7 | C39: {=IF($A39="","",_xlfn.XLOOKUP(1,(Table1[Line Item]=$A39)*(Table1[Fiscal Year]=VALUE(RIGHT(C$3,4))),Table1[Value],"Not found"))} -> 6.75 | D39: {=IF($A39="","",_xlfn.XLOOKUP(1,(Table1[Line Item]=$A39)*(Table1[Fiscal Year]=VALUE(RIGHT(D$3,4))),Table1[Value],"Not found"))} -> 8.42 | E39: {=IF($A39="","",_xlfn.XLOOKUP(1,(Table1[Line Item]=$A39)*(Table1[Fiscal Year]=VALUE(RIGHT(E$3,4))),Table1[Value],"Not found"))} -> 9.44 | F39: {=IF($A39="","",_xlfn.XLOOKUP(1,(Table1[Line Item]=$A39)*(Table1[Fiscal Year]=VALUE(RIGHT(F$3,4))),Table1[Value],"Not found"))} -> 1.78 | G39: {=IF($A39="","",_xlfn.XLOOKUP(1,(Table1[Line Item]=$A39)*(Table1[Fiscal Year]=VALUE(RIGHT(G$3,4))),Table1[Value],"Not found"))} -> 7.36 | H39: {=IF($A39="","",_xlfn.XLOOKUP(1,(Table1[Line Item]=$A39)*(Table1[Fiscal Year]=VALUE(RIGHT(H$3,4))),Table1[Value],"Not found"))} -> 0.27 | I39: {=IF($A39="","",_xlfn.XLOOKUP(1,(Table1[Line Item]=$A39)*(Table1[Fiscal Year]=VALUE(RIGHT(I$3,4))),Table1[Value],"Not found"))} -> -0.18
A40: Wtd. Avg Shares - Basic (mn) | B40: {=IF($A40="","",_xlfn.XLOOKUP(1,(Table1[Line Item]=$A40)*(Table1[Fiscal Year]=VALUE(RIGHT(B$3,4))),Table1[Value],"Not found"))} -> 201 | C40: {=IF($A40="","",_xlfn.XLOOKUP(1,(Table1[Line Item]=$A40)*(Table1[Fiscal Year]=VALUE(RIGHT(C$3,4))),Table1[Value],"Not found"))} -> 202.5 | D40: {=IF($A40="","",_xlfn.XLOOKUP(1,(Table1[Line Item]=$A40)*(Table1[Fiscal Year]=VALUE(RIGHT(D$3,4))),Table1[Value],"Not found"))} -> 200 | E40: {=IF($A40="","",_xlfn.XLOOKUP(1,(Table1[Line Item]=$A40)*(Table1[Fiscal Year]=VALUE(RIGHT(E$3,4))),Table1[Value],"Not found"))} -> 195.7 | F40: {=IF($A40="","",_xlfn.XLOOKUP(1,(Table1[Line Item]=$A40)*(Table1[Fiscal Year]=VALUE(RIGHT(F$3,4))),Table1[Value],"Not found"))} -> 194.3 | G40: {=IF($A40="","",_xlfn.XLOOKUP(1,(Table1[Line Item]=$A40)*(Table1[Fiscal Year]=VALUE(RIGHT(G$3,4))),Table1[Value],"Not found"))} -> 195.8 | H40: {=IF($A40="","",_xlfn.XLOOKUP(1,(Table1[Line Item]=$A40)*(Table1[Fiscal Year]=VALUE(RIGHT(H$3,4))),Table1[Value],"Not found"))} -> 183.5 | I40: {=IF($A40="","",_xlfn.XLOOKUP(1,(Table1[Line Item]=$A40)*(Table1[Fiscal Year]=VALUE(RIGHT(I$3,4))),Table1[Value],"Not found"))} -> 178.6
A41: Wtd. Avg Shares - Diluted (mn) | B41: {=IF($A41="","",_xlfn.XLOOKUP(1,(Table1[Line Item]=$A41)*(Table1[Fiscal Year]=VALUE(RIGHT(B$3,4))),Table1[Value],"Not found"))} -> 201.8 | C41: {=IF($A41="","",_xlfn.XLOOKUP(1,(Table1[Line Item]=$A41)*(Table1[Fiscal Year]=VALUE(RIGHT(C$3,4))),Table1[Value],"Not found"))} -> 203.3 | D41: {=IF($A41="","",_xlfn.XLOOKUP(1,(Table1[Line Item]=$A41)*(Table1[Fiscal Year]=VALUE(RIGHT(D$3,4))),Table1[Value],"Not found"))} -> 200.8 | E41: {=IF($A41="","",_xlfn.XLOOKUP(1,(Table1[Line Item]=$A41)*(Table1[Fiscal Year]=VALUE(RIGHT(E$3,4))),Table1[Value],"Not found"))} -> 196.5 | F41: {=IF($A41="","",_xlfn.XLOOKUP(1,(Table1[Line Item]=$A41)*(Table1[Fiscal Year]=VALUE(RIGHT(F$3,4))),Table1[Value],"Not found"))} -> 195.1 | G41: {=IF($A41="","",_xlfn.XLOOKUP(1,(Table1[Line Item]=$A41)*(Table1[Fiscal Year]=VALUE(RIGHT(G$3,4))),Table1[Value],"Not found"))} -> 196.6 | H41: {=IF($A41="","",_xlfn.XLOOKUP(1,(Table1[Line Item]=$A41)*(Table1[Fiscal Year]=VALUE(RIGHT(H$3,4))),Table1[Value],"Not found"))} -> 184.2 | I41: {=IF($A41="","",_xlfn.XLOOKUP(1,(Table1[Line Item]=$A41)*(Table1[Fiscal Year]=VALUE(RIGHT(I$3,4))),Table1[Value],"Not found"))} -> 179.3
A42: Dividend Per Share (dps) | B42: {=IF($A42="","",_xlfn.XLOOKUP(1,(Table1[Line Item]=$A42)*(Table1[Fiscal Year]=VALUE(RIGHT(B$3,4))),Table1[Value],"Not found"))} -> 2 | C42: {=IF($A42="","",_xlfn.XLOOKUP(1,(Table1[Line Item]=$A42)*(Table1[Fiscal Year]=VALUE(RIGHT(C$3,4))),Table1[Value],"Not found"))} -> 2.6 | D42: {=IF($A42="","",_xlfn.XLOOKUP(1,(Table1[Line Item]=$A42)*(Table1[Fiscal Year]=VALUE(RIGHT(D$3,4))),Table1[Value],"Not found"))} -> 3.35 | E42: {=IF($A42="","",_xlfn.XLOOKUP(1,(Table1[Line Item]=$A42)*(Table1[Fiscal Year]=VALUE(RIGHT(E$3,4))),Table1[Value],"Not found"))} -> 3.85 | F42: {=IF($A42="","",_xlfn.XLOOKUP(1,(Table1[Line Item]=$A42)*(Table1[Fiscal Year]=VALUE(RIGHT(F$3,4))),Table1[Value],"Not found"))} -> 0 | G42: {=IF($A42="","",_xlfn.XLOOKUP(1,(Table1[Line Item]=$A42)*(Table1[Fiscal Year]=VALUE(RIGHT(G$3,4))),Table1[Value],"Not found"))} -> 3.3 | H42: {=IF($A42="","",_xlfn.XLOOKUP(1,(Table1[Line Item]=$A42)*(Table1[Fiscal Year]=VALUE(RIGHT(H$3,4))),Table1[Value],"Not found"))} -> 0.7 | I42: {=IF($A42="","",_xlfn.XLOOKUP(1,(Table1[Line Item]=$A42)*(Table1[Fiscal Year]=VALUE(RIGHT(I$3,4))),Table1[Value],"Not found"))} -> 0.7

Sheet Stage7-chart1
A1: FY | B1: ='Formatted Master P&L(Stasge7)'!B3 -> FY2016 | C1: ='Formatted Master P&L(Stasge7)'!C3 -> FY2017 | D1: ='Formatted Master P&L(Stasge7)'!D3 -> FY2018 | E1: ='Formatted Master P&L(Stasge7)'!E3 -> FY2019 | F1: ='Formatted Master P&L(Stasge7)'!F3 -> FY2020 | G1: ='Formatted Master P&L(Stasge7)'!G3 -> FY2021 | H1: ='Formatted Master P&L(Stasge7)'!H3 -> FY2022 | I1: ='Formatted Master P&L(Stasge7)'!I3 -> FY2023
A2: Revenue | B2: ='MASTER P&L'!B6 -> 18483 | C2: ='MASTER P&L'!C6 -> 21218 | D2: ='MASTER P&L'!D6 -> 21915 | E2: ='MASTER P&L'!E6 -> 23640 | F2: ='MASTER P&L'!F6 -> 19844 | G2: ='MASTER P&L'!G6 -> 21234 | H2: ='MASTER P&L'!H6 -> 22511 | I2: ='MASTER P&L'!I6 -> 21427
A3: Operating Margin | B3: ='Formatted Master P&L(Stasge7)'!B24 -> 0.076124006 | C3: ='Formatted Master P&L(Stasge7)'!C24 -> 0.093552644 | D3: ='Formatted Master P&L(Stasge7)'!D24 -> 0.10773443 | E3: ='Formatted Master P&L(Stasge7)'!E24 -> 0.1108291 | F3: ='Formatted Master P&L(Stasge7)'!F24 -> 0.040465632 | G3: ='Formatted Master P&L(Stasge7)'!G24 -> 0.08665348 | H3: ='Formatted Master P&L(Stasge7)'!H24 -> 0.017191595 | I3: ='Formatted Master P&L(Stasge7)'!I24 -> 0.016567882

Sheet Stage7-chart2
A1: Margin | B1: ='Formatted Master P&L(Stasge7)'!B3 -> FY2016 | C1: ='Formatted Master P&L(Stasge7)'!C3 -> FY2017 | D1: ='Formatted Master P&L(Stasge7)'!D3 -> FY2018 | E1: ='Formatted Master P&L(Stasge7)'!E3 -> FY2019 | F1: ='Formatted Master P&L(Stasge7)'!F3 -> FY2020 | G1: ='Formatted Master P&L(Stasge7)'!G3 -> FY2021 | H1: ='Formatted Master P&L(Stasge7)'!H3 -> FY2022 | I1: ='Formatted Master P&L(Stasge7)'!I3 -> FY2023
A2: Gross Margin | B2: ='Formatted Master P&L(Stasge7)'!B13 -> 0.48601418 | C2: ='Formatted Master P&L(Stasge7)'!C13 -> 0.50400603 | D2: ='Formatted Master P&L(Stasge7)'!D13 -> 0.51599361 | E2: ='Formatted Master P&L(Stasge7)'!E13 -> 0.52000846 | F2: ='Formatted Master P&L(Stasge7)'!F13 -> 0.49697642 | G2: ='Formatted Master P&L(Stasge7)'!G13 -> 0.50499199 | H2: ='Formatted Master P&L(Stasge7)'!H13 -> 0.47301319 | I2: ='Formatted Master P&L(Stasge7)'!I13 -> 0.47500817
A3: Operating Margin | B3: ='Formatted Master P&L(Stasge7)'!B24 -> 0.076124006 | C3: ='Formatted Master P&L(Stasge7)'!C24 -> 0.093552644 | D3: ='Formatted Master P&L(Stasge7)'!D24 -> 0.10773443 | E3: ='Formatted Master P&L(Stasge7)'!E24 -> 0.1108291 | F3: ='Formatted Master P&L(Stasge7)'!F24 -> 0.040465632 | G3: ='Formatted Master P&L(Stasge7)'!G24 -> 0.08665348 | H3: ='Formatted Master P&L(Stasge7)'!H24 -> 0.017191595 | I3: ='Formatted Master P&L(Stasge7)'!I24 -> 0.016567882
A4: Net Margin | B4: ='Formatted Master P&L(Stasge7)'!B36 -> 0.051344479 | C4: ='Formatted Master P&L(Stasge7)'!C36 -> 0.064709209 | D4: ='Formatted Master P&L(Stasge7)'!D36 -> 0.077116131 | E4: ='Formatted Master P&L(Stasge7)'!E36 -> 0.078468697 | F4: ='Formatted Master P&L(Stasge7)'!F36 -> 0.017486394 | G4: ='Formatted Master P&L(Stasge7)'!G36 -> 0.068145427 | H4: ='Formatted Master P&L(Stasge7)'!H36 -> 0.0022211363 | I4: ='Formatted Master P&L(Stasge7)'!I36 -> -0.0015401129

Sheet Stage7-chart3
A1: FY | B1: ='Formatted Master P&L(Stasge7)'!B3 -> FY2016 | C1: ='Formatted Master P&L(Stasge7)'!C3 -> FY2017 | D1: ='Formatted Master P&L(Stasge7)'!D3 -> FY2018 | E1: ='Formatted Master P&L(Stasge7)'!E3 -> FY2019 | F1: ='Formatted Master P&L(Stasge7)'!F3 -> FY2020 | G1: ='Formatted Master P&L(Stasge7)'!G3 -> FY2021 | H1: ='Formatted Master P&L(Stasge7)'!H3 -> FY2022 | I1: ='Formatted Master P&L(Stasge7)'!I3 -> FY2023
A2: Marketing & POS | B2: =ABS('Formatted Master P&L(Stasge7)'!B17)/'Formatted Master P&L(Stasge7)'!B8 -> 0.13699075 | C2: =ABS('Formatted Master P&L(Stasge7)'!C17)/'Formatted Master P&L(Stasge7)'!C8 -> 0.13399001 | D2: =ABS('Formatted Master P&L(Stasge7)'!D17)/'Formatted Master P&L(Stasge7)'!D8 -> 0.13100616 | E2: =ABS('Formatted Master P&L(Stasge7)'!E17)/'Formatted Master P&L(Stasge7)'!E8 -> 0.12800338 | F2: =ABS('Formatted Master P&L(Stasge7)'!F17)/'Formatted Master P&L(Stasge7)'!F8 -> 0.11897803 | G2: =ABS('Formatted Master P&L(Stasge7)'!G17)/'Formatted Master P&L(Stasge7)'!G8 -> 0.12098521 | H2: =ABS('Formatted Master P&L(Stasge7)'!H17)/'Formatted Master P&L(Stasge7)'!H8 -> 0.12398383 | I2: =ABS('Formatted Master P&L(Stasge7)'!I17)/'Formatted Master P&L(Stasge7)'!I8 -> 0.12302235
A3: Distribution & Selling | B3: =ABS('Formatted Master P&L(Stasge7)'!B18)/'Formatted Master P&L(Stasge7)'!B8 -> 0.21798409 | C3: =ABS('Formatted Master P&L(Stasge7)'!C18)/'Formatted Master P&L(Stasge7)'!C8 -> 0.22198134 | D3: =ABS('Formatted Master P&L(Stasge7)'!D18)/'Formatted Master P&L(Stasge7)'!D8 -> 0.22400183 | E3: =ABS('Formatted Master P&L(Stasge7)'!E18)/'Formatted Master P&L(Stasge7)'!E8 -> 0.22301184 | F3: =ABS('Formatted Master P&L(Stasge7)'!F18)/'Formatted Master P&L(Stasge7)'!F8 -> 0.27000605 | G3: =ABS('Formatted Master P&L(Stasge7)'!G18)/'Formatted Master P&L(Stasge7)'!G8 -> 0.23401149 | H3: =ABS('Formatted Master P&L(Stasge7)'!H18)/'Formatted Master P&L(Stasge7)'!H8 -> 0.24299231 | I3: =ABS('Formatted Master P&L(Stasge7)'!I18)/'Formatted Master P&L(Stasge7)'!I8 -> 0.25799225
A4: G&A | B4: =ABS('Formatted Master P&L(Stasge7)'!B19)/'Formatted Master P&L(Stasge7)'!B8 -> 0.053995563 | C4: =ABS('Formatted Master P&L(Stasge7)'!C19)/'Formatted Master P&L(Stasge7)'!C8 -> 0.05302102 | D4: =ABS('Formatted Master P&L(Stasge7)'!D19)/'Formatted Master P&L(Stasge7)'!D8 -> 0.052019165 | E4: =ABS('Formatted Master P&L(Stasge7)'!E19)/'Formatted Master P&L(Stasge7)'!E8 -> 0.056979695 | F4: =ABS('Formatted Master P&L(Stasge7)'!F19)/'Formatted Master P&L(Stasge7)'!F8 -> 0.065007055 | G4: =ABS('Formatted Master P&L(Stasge7)'!G19)/'Formatted Master P&L(Stasge7)'!G8 -> 0.060987096 | H4: =ABS('Formatted Master P&L(Stasge7)'!H19)/'Formatted Master P&L(Stasge7)'!H8 -> 0.078006308 | I4: =ABS('Formatted Master P&L(Stasge7)'!I19)/'Formatted Master P&L(Stasge7)'!I8 -> 0.072992019
A5: Sundry Expenses | B5: =ABS('Formatted Master P&L(Stasge7)'!B20)/'Formatted Master P&L(Stasge7)'!B8 -> 0.010009198 | C5: =ABS('Formatted Master P&L(Stasge7)'!C20)/'Formatted Master P&L(Stasge7)'!C8 -> 0.0099915166 | D5: =ABS('Formatted Master P&L(Stasge7)'!D20)/'Formatted Master P&L(Stasge7)'!D8 -> 0.0099931554 | E5: =ABS('Formatted Master P&L(Stasge7)'!E20)/'Formatted Master P&L(Stasge7)'!E8 -> 0.0099830795 | F5: =ABS('Formatted Master P&L(Stasge7)'!F20)/'Formatted Master P&L(Stasge7)'!F8 -> 0.0099778271 | G5: =ABS('Formatted Master P&L(Stasge7)'!G20)/'Formatted Master P&L(Stasge7)'!G8 -> 0.0099839879 | H5: =ABS('Formatted Master P&L(Stasge7)'!H20)/'Formatted Master P&L(Stasge7)'!H8 -> 0.0099951135 | I5: =ABS('Formatted Master P&L(Stasge7)'!I20)/'Formatted Master P&L(Stasge7)'!I8 -> 0.011994213
A6: Goodwill / Intangible Impairment | B6: =ABS('Formatted Master P&L(Stasge7)'!B22)/'Formatted Master P&L(Stasge7)'!B8 -> 0 | C6: =ABS('Formatted Master P&L(Stasge7)'!C22)/'Formatted Master P&L(Stasge7)'!C8 -> 0 | D6: =ABS('Formatted Master P&L(Stasge7)'!D22)/'Formatted Master P&L(Stasge7)'!D8 -> 0 | E6: =ABS('Formatted Master P&L(Stasge7)'!E22)/'Formatted Master P&L(Stasge7)'!E8 -> 0 | F6: =ABS('Formatted Master P&L(Stasge7)'!F22)/'Formatted Master P&L(Stasge7)'!F8 -> 0 | G6: =ABS('Formatted Master P&L(Stasge7)'!G22)/'Formatted Master P&L(Stasge7)'!G8 -> 0 | H6: =ABS('Formatted Master P&L(Stasge7)'!H22)/'Formatted Master P&L(Stasge7)'!H8 -> 0.008618009 | I6: =ABS('Formatted Master P&L(Stasge7)'!I22)/'Formatted Master P&L(Stasge7)'!I8 -> 0

Sheet Stage7-chart4
A1: Region | B1: FY2019 Restated (€mn) | C1: FY2023 (€mn) | D1: Contribution to Revenue Change (€mn)
A2: EMEA | B2: 8369 | C2: 7585 | D2: -784
A3: North America | B3: 4917 | C3: 5142 | D3: 225
A4: Greater China | B4: 4728 | C4: 3257 | D4: -1471
A5: Asia-Pacific | B5: 2931 | C5: 2807 | D5: -124
A6: Latin America | B6: 1726 | C6: 2057 | D6: 331
A7: Other Businesses | B7: 969 | C7: 579 | D7: -390

Sheet summary sheet (Stage7-Q6)
A1: ADS GY EQUITY — P&L SUMMARY
A2: FY2016–FY2023
B3: FY2023 Revenue | F3: Revenue CAGR | K3: FY2023 Operating Margin | P3: FY2023 Net Margin | T3: Revenue Change
B4: 21427 | F4: 0.0213 | K4: 0.017 | P4: -0.0015401129 | T4: -2213
A22: Big Picture: *Total sales grew slowly from €18.5B in 2016 to €21.4B in 2023. *Sales peaked in 2019 and dropped in both 2020 and 2023. *Store and online sales jumped 66%. *Wholesale store sales fell 4.5%. | H22: Shrinking Profits: *Operating profits fell from 11.1% in 2019 to 1.7% in 2023. *Higher running costs caused this profit squeeze. *The company lost €26 million in 2023. *Earnings per share turned negative in 2023. | P22: Regions & Staff: *Greater China sales dropped by €1.47B from 2019 to 2023. *Latin America sales grew by €331M over the same period. *Sales per worker peaked at €397.1k in 2019. *Worker productivity fell in 2020 and dipped again in 2023.

Sheet PBI_Product
A1: BY PRODUCT CATEGORY | B1: FY2016 | C1: FY2017 | D1: FY2018 | E1: FY2019 | F1: FY2020 | G1: FY2021 | H1: FY2022 | I1: FY2023
A2: Footwear | B2: 10,073.0 | C2: 11,712.0 | D2: 12,272.0 | E2: 13,380.0 | F2: 11,629.0 | G2: 12,252.0 | H2: 12,831.0 | I2: 12,470.0
A3: Apparel | B3: 7,264.0 | C3: 8,190.0 | D3: 8,306.0 | E3: 8,865.0 | F3: 7,104.0 | G3: 7,772.0 | H3: 8,397.0 | I3: 7,757.0
A4: Acc. & Gear | B4: 1,146.0 | C4: 1,316.0 | D4: 1,337.0 | E4: 1,395.0 | F4: 1,111.0 | G4: 1,210.0 | H4: 1,283.0 | I4: 1,200.0
A5: Footwear | B5: 10,073.0 | C5: 11,712.0 | D5: 12,272.0 | E5: 13,380.0 | F5: 11,629.0 | G5: 12,252.0 | H5: 12,831.0 | I5: 12,470.0

Sheet PBI_P&L
A1: Line Item | B1: Statement Group | C1: Sign Convention | D1: FY2016 | E1: FY2017 | F1: FY2018 | G1: FY2019 | H1: FY2020 | I1: FY2021 | J1: FY2022 | K1: FY2023
A2: Wholesale | B2: =_xlfn.XLOOKUP(A2,'lookup tables'!$A$2:$A$28,'lookup tables'!$B$2:$B$28,"Not Found",0) -> Revenue | C2: =_xlfn.XLOOKUP(A2,'lookup tables'!$A$2:$A$28,'lookup tables'!$C$2:$C$28,"Not Found",0) -> Positive | D2: 11663 | E2: 12943 | F2: 12733 | G2: 13191 | H2: 10160 | I2: 11148 | J2: 12156 | K2: 11142
A3: Retail | B3: =_xlfn.XLOOKUP(A3,'lookup tables'!$A$2:$A$28,'lookup tables'!$B$2:$B$28,"Not Found",0) -> Revenue | C3: =_xlfn.XLOOKUP(A3,'lookup tables'!$A$2:$A$28,'lookup tables'!$C$2:$C$28,"Not Found",0) -> Positive | D3: 5841 | E3: 7172 | F3: 8196 | G3: 9480 | H3: 8970 | I3: 9428 | J3: 9725 | K3: 9706
A4: Other Businesses | B4: =_xlfn.XLOOKUP(A4,'lookup tables'!$A$2:$A$28,'lookup tables'!$B$2:$B$28,"Not Found",0) -> Revenue | C4: =_xlfn.XLOOKUP(A4,'lookup tables'!$A$2:$A$28,'lookup tables'!$C$2:$C$28,"Not Found",0) -> Positive | D4: 979 | E4: 1103 | F4: 986 | G4: 969 | H4: 714 | I4: 658 | J4: 630 | K4: 579
A5: Total Net Revenue | B5: =_xlfn.XLOOKUP(A5,'lookup tables'!$A$2:$A$28,'lookup tables'!$B$2:$B$28,"Not Found",0) -> Revenue | C5: =_xlfn.XLOOKUP(A5,'lookup tables'!$A$2:$A$28,'lookup tables'!$C$2:$C$28,"Not Found",0) -> Positive | D5: 18483 | E5: 21218 | F5: 21915 | G5: 23640 | H5: 19844 | I5: 21234 | J5: 22511 | K5: 21427
A6: Cost of Goods Sold | B6: =_xlfn.XLOOKUP(A6,'lookup tables'!$A$2:$A$28,'lookup tables'!$B$2:$B$28,"Not Found",0) -> Cost | C6: =_xlfn.XLOOKUP(A6,'lookup tables'!$A$2:$A$28,'lookup tables'!$C$2:$C$28,"Not Found",0) -> Negative | D6: -9500 | E6: -10524 | F6: -10607 | G6: -11347 | H6: -9982 | I6: -10511 | J6: -11863 | K6: -11249
A7: Gross Profit | B7: =_xlfn.XLOOKUP(A7,'lookup tables'!$A$2:$A$28,'lookup tables'!$B$2:$B$28,"Not Found",0) -> Subtotal | C7: =_xlfn.XLOOKUP(A7,'lookup tables'!$A$2:$A$28,'lookup tables'!$C$2:$C$28,"Not Found",0) -> Positive | D7: 8983 | E7: 10694 | F7: 11308 | G7: 12293 | H7: 9862 | I7: 10723 | J7: 10648 | K7: 10178
A8: Royalty and Commission Income | B8: =_xlfn.XLOOKUP(A8,'lookup tables'!$A$2:$A$28,'lookup tables'!$B$2:$B$28,"Not Found",0) -> Other income | C8: =_xlfn.XLOOKUP(A8,'lookup tables'!$A$2:$A$28,'lookup tables'!$C$2:$C$28,"Not Found",0) -> Positive | D8: 108 | E8: 115 | F8: 121 | G8: 130 | H8: 96 | I8: 104 | J8: 112 | K8: 107
A9: Other Operating Income | B9: =_xlfn.XLOOKUP(A9,'lookup tables'!$A$2:$A$28,'lookup tables'!$B$2:$B$28,"Not Found",0) -> Other income | C9: =_xlfn.XLOOKUP(A9,'lookup tables'!$A$2:$A$28,'lookup tables'!$C$2:$C$28,"Not Found",0) -> Positive | D9: 60 | E9: 66 | F9: 71 | G9: 78 | H9: 52 | I9: 58 | J9: 63 | K9: 55
A10: Marketing and Point-of-Sale | B10: =_xlfn.XLOOKUP(A10,'lookup tables'!$A$2:$A$28,'lookup tables'!$B$2:$B$28,"Not Found",0) -> Operating expense | C10: =_xlfn.XLOOKUP(A10,'lookup tables'!$A$2:$A$28,'lookup tables'!$C$2:$C$28,"Not Found",0) -> Negative | D10: -2532 | E10: -2843 | F10: -2871 | G10: -3026 | H10: -2361 | I10: -2569 | J10: -2791 | K10: -2636
A11: Distribution and Selling Expense | B11: =_xlfn.XLOOKUP(A11,'lookup tables'!$A$2:$A$28,'lookup tables'!$B$2:$B$28,"Not Found",0) -> Operating expense | C11: =_xlfn.XLOOKUP(A11,'lookup tables'!$A$2:$A$28,'lookup tables'!$C$2:$C$28,"Not Found",0) -> Negative | D11: -4029 | E11: -4710 | F11: -4909 | G11: -5272 | H11: -5358 | I11: -4969 | J11: -5470 | K11: -5528
A12: General & Administration | B12: =_xlfn.XLOOKUP(A12,'lookup tables'!$A$2:$A$28,'lookup tables'!$B$2:$B$28,"Not Found",0) -> Operating expense | C12: =_xlfn.XLOOKUP(A12,'lookup tables'!$A$2:$A$28,'lookup tables'!$C$2:$C$28,"Not Found",0) -> Negative | D12: -998 | E12: -1125 | F12: -1140 | G12: -1347 | H12: -1290 | I12: -1295 | J12: -1756 | K12: -1564
A13: Sundry Expenses | B13: =_xlfn.XLOOKUP(A13,'lookup tables'!$A$2:$A$28,'lookup tables'!$B$2:$B$28,"Not Found",0) -> Operating expense | C13: =_xlfn.XLOOKUP(A13,'lookup tables'!$A$2:$A$28,'lookup tables'!$C$2:$C$28,"Not Found",0) -> Negative | D13: -185 | E13: -212 | F13: -219 | G13: -236 | H13: -198 | I13: -212 | J13: -225 | K13: -257
... A29: Dividend Per Share (dps) | B29: =_xlfn.XLOOKUP(A29,'lookup tables'!$A$2:$A$28,'lookup tables'!$B$2:$B$28,"Not Found",0) -> Per share | C29: =_xlfn.XLOOKUP(A29,'lookup tables'!$A$2:$A$28,'lookup tables'!$C$2:$C$28,"Not Found",0) -> Positive | D29: 2 | E29: 2.6 | F29: 3.35 | G29: 3.85 | H29: 0 | I29: 3.3 | J29: 0.7 | K29: 0.7

Sheet PBI_Region
A1: Region | B1: FY2019 Restated (€mn) | C1: FY2023 (€mn)
A2: EMEA | B2: 8369 | C2: 7585
A3: North America | B3: 4917 | C3: 5142
A4: Greater China | B4: 4728 | C4: 3257
A5: Asia-Pacific | B5: 2931 | C5: 2807
A6: Latin America | B6: 1726 | C6: 2057
A7: Other Businesses | B7: 969 | C7: 579

Sheet PBI_reg
A1: Region | B1: FY2016 | C1: FY2017 | D1: FY2018 | E1: FY2019 | F1: FY2020 | G1: FY2021 | H1: FY2022 | I1: FY2023
A2: EMEA | B2: 7393 | C2: 7956 | D2: 7955 | E2: 8369 | F2: 7005 | G2: 7432 | H2: 7879 | I2: 7585
A3: North America | B3: 3068 | C3: 3947 | D3: 4361 | E3: 4917 | F3: 4127 | G3: 5330 | H3: 5921 | I3: 5142
A4: Greater China | B4: 2976 | C4: 3756 | D4: 4164 | E4: 4728 | F4: 4346 | G4: 4247 | H4: 3534 | I4: 3257
A5: Asia-Pacific | B5: 2421 | C5: 2716 | D5: 2761 | E5: 2931 | F5: 2342 | G5: 2060 | H5: 2656 | I5: 2807
A6: Latin America | B6: 1645 | C6: 1740 | D6: 1688 | E6: 1726 | F6: 1310 | G6: 1507 | H6: 1891 | I6: 2057
A7: Other Businesses | B7: 980 | C7: 1103 | D7: 986 | E7: 969 | F7: 714 | G7: 658 | H7: 630 | I7: 579

Sheet PBI_Brand
A1: BY BRAND | B1: FY2016 | C1: FY2017 | D1: FY2018 | E1: FY2019 | F1: FY2020 | G1: FY2021 | H1: FY2022 | I1: FY2023
A2: adidas | B2: 16,746.0 | C2: 19,457.0 | D2: 20,271.0 | E2: 21,985.0 | F2: 18,614.0 | G2: 20,045.0 | H2: 22,511.0 | I2: 21,427.0
A3: Reebok | B3: 1,737.0 | C3: 1,761.0 | D3: 1,644.0 | E3: 1,655.0 | F3: 1,230.0 | G3: 1,189.0

Sheet PBI_Employee
A1: Fiscal Year | B1: Total Revenue (€mn) | C1: Employees (FTE)
A2: FY2016 | B2: 18483 | C2: 60617
A3: FY2017 | B3: 21218 | C3: 56888
A4: FY2018 | B4: 21915 | C4: 57016
A5: FY2019 | B5: 23640 | C5: 59533
A6: FY2020 | B6: 19844 | C6: 62285
A7: FY2021 | B7: 21234 | C7: 61401
A8: FY2022 | B8: 22511 | C8: 59258
A9: FY2023 | B9: 21427 | C9: 57069

Sheet PBI_DISTRIBUTION CHANNEL
A1: BY DISTRIBUTION CHANNEL | B1: FY2016 | C1: FY2017 | D1: FY2018 | E1: FY2019 | F1: FY2020 | G1: FY2021 | H1: FY2022 | I1: FY2023
A2: Wholesale | B2: 11,663.0 | C2: 12,943.0 | D2: 12,733.0 | E2: 13,191.0 | F2: 10,160.0 | G2: 11,148.0 | H2: 12,156.0 | I2: 11,142.0
A3: Retail | B3: 5,841.0 | C3: 7,172.0 | D3: 8,196.0 | E3: 9,480.0 | F3: 8,970.0 | G3: 9,428.0 | H3: 9,725.0 | I3: 9,706.0
A4: Other Businesses | B4: 979.0 | C4: 1,103.0 | D4: 986.0 | E4: 969.0 | F4: 714.0 | G4: 658.0 | H4: 630.0 | I4: 579.0
